Workbook

Sheet TABELA
D2: PREENCHA O SEU ESTADO E SE ESTÁ ENQUADRADO NO REGIME SIMPLES OU NÃO
J3: CNPJ:
J5: UF: | K5: PR
J7: Regime SIMPLES? | K7: NÃO
E8: PEDIDOS SÃO FEITOS SOMENTE EM CAIXA | L8: (*) quando inside ST o valor do imposto é adicionado nesta coluna
B9: =PREÇOS!A1 -> 0325E
B10: Descrição | D10: Código | E10: QUANTIDADE (Caixas) | F10: Valor UN | G10: SUBSTITUIÇÃO TRIBUTÁRIA UN | H10: Valor UN + ST | I10: Valor Caixa | J10: Valor Caixa + ST | K10: Valor TOTAL | L10: Valor TOTAL + ST (*) | M10: Preço sugerido
B11: Papinha Papapa Carne Arroz Legumes 120g | D11: 5313 | F11: =VLOOKUP($K$5,PREÇOS!$A$2:$L$31,9,FALSE) -> 7.6855 | G11: 0 | H11: =SUM(F11:G11) -> 7.6855 | I11: =F11*12 -> 92.226 | J11: =(F11+G11)*12 -> 92.226 | K11: =E11*I11 -> 0 | L11: =E11*J11 -> 0 | M11: =VLOOKUP($K$5,PSC!$A$2:$L$31,9,FALSE) -> 12.49
B12: Papinha Papapa Frango Grão Vegetais 120g | D12: 5320 | F12: =VLOOKUP($K$5,PREÇOS!$A$2:$L$31,9,FALSE) -> 7.6855 | G12: 0 | H12: =SUM(F12:G12) -> 7.6855 | I12: =F12*12 -> 92.226 | J12: =(F12+G12)*12 -> 92.226 | K12: =E12*I12 -> 0 | L12: =E12*J12 -> 0 | M12: =VLOOKUP($K$5,PSC!$A$2:$L$31,9,FALSE) -> 12.49
B14: Papinha Papapa Iogurte Frutas Amarelas e Banana 100g | D14: 5566 | F14: =VLOOKUP($K$5,PREÇOS!$A$2:$M$31,13,FALSE) -> 5.3865 | G14: 0 | H14: =SUM(F14:G14) -> 5.3865 | I14: =F14*16 -> 86.184 | J14: =I14 -> 86.184 | K14: =E14*I14 -> 0 | L14: =E14*J14 -> 0 | M14: =VLOOKUP($K$5,PSC!$A$2:$M$31,13,FALSE) -> 9.49
B15: Papinha Papapa Iogurte Frutas Vermelhas e Banana 100g | D15: 5573 | F15: =VLOOKUP($K$5,PREÇOS!$A$2:$M$31,13,FALSE) -> 5.3865 | G15: 0 | H15: =SUM(F15:G15) -> 5.3865 | I15: =F15*16 -> 86.184 | J15: =I15 -> 86.184 | K15: =E15*I15 -> 0 | L15: =E15*J15 -> 0 | M15: =VLOOKUP($K$5,PSC!$A$2:$M$31,13,FALSE) -> 9.49
B17: Papinha Papapá Org Maçã Ameixa 100g | D17: 17898994908729 | F17: =VLOOKUP($K$5,PREÇOS!$A$2:$L$31,2,FALSE) -> 5.928 | G17: 0 | H17: =SUM(F17:G17) -> 5.928 | I17: =F17*12 -> 71.136 | J17: =I17 -> 71.136 | K17: =E17*I17 -> 0 | L17: =E17*J17 -> 0 | M17: =VLOOKUP($K$5,PSC!$A$2:$L$31,2,FALSE) -> 9.49
B18: Papinha Papapá Org Banana Mirtilo Quinoa 100g | D18: 17898994908736 | F18: =VLOOKUP($K$5,PREÇOS!$A$2:$L$31,2,FALSE) -> 5.928 | G18: 0 | H18: =SUM(F18:G18) -> 5.928 | I18: =F18*12 -> 71.136 | J18: =I18 -> 71.136 | K18: =E18*I18 -> 0 | L18: =E18*J18 -> 0 | M18: =VLOOKUP($K$5,PSC!$A$2:$L$31,2,FALSE) -> 9.49
B19: Papinha Papapá Org Manga 100g | D19: 17898994908712 | F19: =VLOOKUP($K$5,PREÇOS!$A$2:$L$31,2,FALSE) -> 5.928 | G19: 0 | H19: =SUM(F19:G19) -> 5.928 | I19: =F19*12 -> 71.136 | J19: =I19 -> 71.136 | K19: =E19*I19 -> 0 | L19: =E19*J19 -> 0 | M19: =VLOOKUP($K$5,PSC!$A$2:$L$31,2,FALSE) -> 9.49
B20: Papinha Papapá Org Pera Espinafre Abobrinha 100g | D20: 17898994908750 | F20: =VLOOKUP($K$5,PREÇOS!$A$2:$L$31,2,FALSE) -> 5.928 | G20: 0 | H20: =SUM(F20:G20) -> 5.928 | I20: =F20*12 -> 71.136 | J20: =I20 -> 71.136 | K20: =E20*I20 -> 0 | L20: =E20*J20 -> 0 | M20: =VLOOKUP($K$5,PSC!$A$2:$L$31,2,FALSE) -> 9.49
B21: Papinha Papapá Org Maçã B. Doce Cenoura 100g | D21: 27898994908757 | F21: =VLOOKUP($K$5,PREÇOS!$A$2:$L$31,2,FALSE) -> 5.928 | G21: 0 | H21: =SUM(F21:G21) -> 5.928 | I21: =F21*12 -> 71.136 | J21: =I21 -> 71.136 | K21: =E21*I21 -> 0 | L21: =E21*J21 -> 0 | M21: =VLOOKUP($K$5,PSC!$A$2:$L$31,2,FALSE) -> 9.49
B22: Papinha Papapá Org Morango Maçã 100g | D22: 5306 | F22: =VLOOKUP($K$5,PREÇOS!$A$2:$L$31,2,FALSE) -> 5.928 | G22: 0 | H22: =SUM(F22:G22) -> 5.928 | I22: =F22*12 -> 71.136 | J22: =I22 -> 71.136 | K22: =E22*I22 -> 0 | L22: =E22*J22 -> 0 | M22: =VLOOKUP($K$5,PSC!$A$2:$L$31,2,FALSE) -> 9.49
B24: Biscoito inf Papapá Palitinho de Vegetais org. Beterraba 20g | D24: 5085 | F24: =VLOOKUP($K$5,PREÇOS!$A$2:$L$31,3,FALSE) -> 3.591 | G24: =IF($K$7="SIM",VLOOKUP($K$5,'ST PALITINHOS'!$A$1:$J$31,10,FALSE),VLOOKUP($K$5,'ST PALITINHOS'!$A$1:$J$31,9,FALSE)) -> 0.75039331 | H24: =SUM(F24:G24) -> 4.3413933 | I24: =F24*16 -> 57.456 | J24: =(F24+G24)*16 -> 69.462293 | K24: =E24*I24 -> 0 | L24: =E24*J24 -> 0 | M24: =VLOOKUP($K$5,PSC!$A$2:$L$31,3,FALSE) -> 5.79
B25: Biscoito inf Papapá Palitinho de Vegetais org. Cenoura 20g | D25: 5078 | F25: =VLOOKUP($K$5,PREÇOS!$A$2:$L$31,3,FALSE) -> 3.591 | G25: =IF($K$7="SIM",VLOOKUP($K$5,'ST PALITINHOS'!$A$1:$J$31,10,FALSE),VLOOKUP($K$5,'ST PALITINHOS'!$A$1:$J$31,9,FALSE)) -> 0.75039331 | H25: =SUM(F25:G25) -> 4.3413933 | I25: =F25*16 -> 57.456 | J25: =(F25+G25)*16 -> 69.462293 | K25: =E25*I25 -> 0 | L25: =E25*J25 -> 0 | M25: =VLOOKUP($K$5,PSC!$A$2:$L$31,3,FALSE) -> 5.79
B26: Biscoito inf Papapá Palitinho de Vegetais org. Tomate/Manjericão 20g | D26: 5061 | F26: =VLOOKUP($K$5,PREÇOS!$A$2:$L$31,3,FALSE) -> 3.591 | G26: =IF($K$7="SIM",VLOOKUP($K$5,'ST PALITINHOS'!$A$1:$J$31,10,FALSE),VLOOKUP($K$5,'ST PALITINHOS'!$A$1:$J$31,9,FALSE)) -> 0.75039331 | H26: =SUM(F26:G26) -> 4.3413933 | I26: =F26*16 -> 57.456 | J26: =(F26+G26)*16 -> 69.462293 | K26: =E26*I26 -> 0 | L26: =E26*J26 -> 0 | M26: =VLOOKUP($K$5,PSC!$A$2:$L$31,3,FALSE) -> 5.79
B28: Biscoito Inf Papapá dent. Maçã e Abóbora 36g | D28: 8774 | F28: =VLOOKUP($K$5,PREÇOS!$A$2:$L$31,4,FALSE) -> 11.951 | G28: =IF($K$7="SIM",VLOOKUP($K$5,'ST BISCOITINHOS'!$A$1:$J$31,10,FALSE),VLOOKUP($K$5,'ST BISCOITINHOS'!$A$1:$J$31,9,FALSE)) -> 0 | H28: =SUM(F28:G28) -> 11.951 | I28: =F28*12 -> 143.412 | J28: =(F28+G28)*12 -> 143.412 | K28: =E28*I28 -> 0 | L28: =E28*J28 -> 0 | M28: =VLOOKUP($K$5,PSC!$A$2:$L$31,4,FALSE) -> 19.99
B29: Biscoito Inf Papapá dent Vegetais 36g | D29: 8767 | F29: =VLOOKUP($K$5,PREÇOS!$A$2:$L$31,4,FALSE) -> 11.951 | G29: =IF($K$7="SIM",VLOOKUP($K$5,'ST BISCOITINHOS'!$A$1:$J$31,10,FALSE),VLOOKUP($K$5,'ST BISCOITINHOS'!$A$1:$J$31,9,FALSE)) -> 0 | H29: =SUM(F29:G29) -> 11.951 | I29: =F29*12 -> 143.412 | J29: =(F29+G29)*12 -> 143.412 | K29: =E29*I29 -> 0 | L29: =E29*J29 -> 0 | M29: =VLOOKUP($K$5,PSC!$A$2:$L$31,4,FALSE) -> 19.99
B31: Macarrao Inf Papapá m. Elbow Quinoa 200g | D31: 5290 | F31: =VLOOKUP($K$5,PREÇOS!$A$2:$L$31,5,FALSE) -> 8.0275 | G31: =IF($K$7="SIM",VLOOKUP($K$5,'ST PAPAPASTA'!$A$1:$J$31,10,FALSE),VLOOKUP($K$5,'ST PAPAPASTA'!$A$1:$J$31,9,FALSE)) -> 0 | H31: =SUM(F31:G31) -> 8.0275 | I31: =F31*12 -> 96.33 | J31: =(F31+G31)*12 -> 96.33 | K31: =E31*I31 -> 0 | L31: =E31*J31 -> 0 | M31: =VLOOKUP($K$5,PSC!$A$2:$L$31,5,FALSE) -> 13.69
B32: Macarrao Inf Papapá m. Fusilli Vegetais 200g | D32: 5283 | F32: =VLOOKUP($K$5,PREÇOS!$A$2:$L$31,5,FALSE) -> 8.0275 | G32: =IF($K$7="SIM",VLOOKUP($K$5,'ST PAPAPASTA'!$A$1:$J$31,10,FALSE),VLOOKUP($K$5,'ST PAPAPASTA'!$A$1:$J$31,9,FALSE)) -> 0 | H32: =SUM(F32:G32) -> 8.0275 | I32: =F32*12 -> 96.33 | J32: =(F32+G32)*12 -> 96.33 | K32: =E32*I32 -> 0 | L32: =E32*J32 -> 0 | M32: =VLOOKUP($K$5,PSC!$A$2:$L$31,5,FALSE) -> 13.69
B34: Sopinha Papapá org Lentinha Carne Legumes 180g | D34: 5276 | F34: =VLOOKUP($K$5,PREÇOS!$A$2:$L$31,6,FALSE) -> 11.21 | G34: 0 | H34: =SUM(F34:G34) -> 11.21 | I34: =F34*6 -> 67.26 | J34: =(F34+G34)*6 -> 67.26 | K34: =E34*I34 -> 0 | L34: =E34*J34 -> 0 | M34: =VLOOKUP($K$5,PSC!$A$2:$L$31,6,FALSE) -> 17.99
B35: Risotinho Papapá org Arroz quinoa frango 180g | D35: 5269 | F35: =VLOOKUP($K$5,PREÇOS!$A$2:$L$31,6,FALSE) -> 11.21 | G35: 0 | H35: =SUM(F35:G35) -> 11.21 | I35: =F35*6 -> 67.26 | J35: =(F35+G35)*6 -> 67.26 | K35: =E35*I35 -> 0 | L35: =E35*J35 -> 0 | M35: =VLOOKUP($K$5,PSC!$A$2:$L$31,6,FALSE) -> 17.99
B36: Caseirinho Papapá org Arroz feijão carne leg. 180g | D36: 5252 | F36: =VLOOKUP($K$5,PREÇOS!$A$2:$L$31,6,FALSE) -> 11.21 | G36: 0 | H36: =SUM(F36:G36) -> 11.21 | I36: =F36*6 -> 67.26 | J36: =(F36+G36)*6 -> 67.26 | K36: =E36*I36 -> 0 | L36: =E36*J36 -> 0 | M36: =VLOOKUP($K$5,PSC!$A$2:$L$31,6,FALSE) -> 17.99
B38: Cereal Infantil Papapá Aveia - Morango e Beterraba 170g caixa | D38: 3344 | F38: =VLOOKUP($K$5,PREÇOS!$A$2:$L$31,7,FALSE) -> 7.885 | G38: =IF($K$7="SIM",VLOOKUP($K$5,'ST CEREAL'!$A$1:$J$31,10,FALSE),VLOOKUP($K$5,'ST CEREAL'!$A$1:$J$31,9,FALSE)) -> 1.5262206 | H38: =SUM(F38:G38) -> 9.4112206 | I38: =F38*12 -> 94.62 | J38: =(F38+G38)*12 -> 112.93465 | K38: =E38*I38 -> 0 | L38: =E38*J38 -> 0 | M38: =VLOOKUP($K$5,PSC!$A$2:$L$31,7,FALSE) -> 13.89
B39: Cereal Infantil Papapá Aveia - Banana e Ameixa 170g caixa | D39: 3343 | F39: =VLOOKUP($K$5,PREÇOS!$A$2:$L$31,7,FALSE) -> 7.885 | G39: =IF($K$7="SIM",VLOOKUP($K$5,'ST CEREAL'!$A$1:$J$31,10,FALSE),VLOOKUP($K$5,'ST CEREAL'!$A$1:$J$31,9,FALSE)) -> 1.5262206 | H39: =SUM(F39:G39) -> 9.4112206 | I39: =F39*12 -> 94.62 | J39: =(F39+G39)*12 -> 112.93465 | K39: =E39*I39 -> 0 | L39: =E39*J39 -> 0 | M39: =VLOOKUP($K$5,PSC!$A$2:$L$31,7,FALSE) -> 13.89
B40: Cereal Infantil Papapá Aveia - Multicereais 170g caixa | D40: 5382 | F40: =VLOOKUP($K$5,PREÇOS!$A$2:$L$31,7,FALSE) -> 7.885 | G40: =IF($K$7="SIM",VLOOKUP($K$5,'ST CEREAL'!$A$1:$J$31,10,FALSE),VLOOKUP($K$5,'ST CEREAL'!$A$1:$J$31,9,FALSE)) -> 1.5262206 | H40: =SUM(F40:G40) -> 9.4112206 | I40: =F40*12 -> 94.62 | J40: =(F40+G40)*12 -> 112.93465 | K40: =E40*I40 -> 0 | L40: =E40*J40 -> 0 | M40: =VLOOKUP($K$5,PSC!$A$2:$L$31,7,FALSE) -> 13.89
B41: Cereal Infantil Papapá Aveia - Morango e Beterraba sache 170g | D41: 5402 | F41: =VLOOKUP($K$5,PREÇOS!$A$2:$L$31,10,FALSE) -> 5.8425 | G41: =IF($K$7="SIM",VLOOKUP($K$5,'ST CEREAL'!$A$1:$J$31,10,FALSE),VLOOKUP($K$5,'ST CEREAL'!$A$1:$J$31,9,FALSE)) -> 1.5262206 | H41: =SUM(F41:G41) -> 7.3687206 | I41: =F41*12 -> 70.11 | J41: =(F41+G41)*12 -> 88.424647 | K41: =E41*I41 -> 0 | L41: =E41*J41 -> 0 | M41: =VLOOKUP($K$5,PSC!$A$2:$L$31,10,FALSE) -> 9.99
B42: Cereal Infantil Papapá Aveia - Banana e Ameixa sache 170g | D42: 5419 | F42: =VLOOKUP($K$5,PREÇOS!$A$2:$L$31,10,FALSE) -> 5.8425 | G42: =IF($K$7="SIM",VLOOKUP($K$5,'ST CEREAL'!$A$1:$J$31,10,FALSE),VLOOKUP($K$5,'ST CEREAL'!$A$1:$J$31,9,FALSE)) -> 1.5262206 | H42: =SUM(F42:G42) -> 7.3687206 | I42: =F42*12 -> 70.11 | J42: =(F42+G42)*12 -> 88.424647 | K42: =E42*I42 -> 0 | L42: =E42*J42 -> 0 | M42: =VLOOKUP($K$5,PSC!$A$2:$L$31,10,FALSE) -> 9.99
B43: Cereal Infantil Papapá Aveia - Multicereais sache 170g | D43: 5429 | F43: =VLOOKUP($K$5,PREÇOS!$A$2:$L$31,11,FALSE) -> 5.8425 | G43: =IF($K$7="SIM",VLOOKUP($K$5,'ST CEREAL'!$A$1:$J$31,10,FALSE),VLOOKUP($K$5,'ST CEREAL'!$A$1:$J$31,9,FALSE)) -> 1.5262206 | H43: =SUM(F43:G43) -> 7.3687206 | I43: =F43*12 -> 70.11 | J43: =(F43+G43)*12 -> 88.424647 | K43: =E43*I43 -> 0 | L43: =E43*J43 -> 0 | M43: =VLOOKUP($K$5,PSC!$A$2:$L$31,11,FALSE) -> 9.99
B44: Cereal Infantil Papapá Aveia - Multicereais sache 500g | D44: 5399 | F44: =VLOOKUP($K$5,PREÇOS!$A$2:$L$31,12,FALSE) -> 14.2405 | G44: =IF($K$7="SIM",VLOOKUP($K$5,'ST CEREAL'!$A$1:$J$31,10,FALSE),VLOOKUP($K$5,'ST CEREAL'!$A$1:$J$31,9,FALSE)) -> 1.5262206 | H44: =SUM(F44:G44) -> 15.766721 | I44: =F44*12 -> 170.886 | J44: =(F44+G44)*12 -> 189.20065 | K44: =E44*I44 -> 0 | L44: =E44*J44 -> 0 | M44: =VLOOKUP($K$5,PSC!$A$2:$L$31,12,FALSE) -> 24.99
B46: Biscoito Infantil Papapá Biscotti com Laranja e Cenoura 60g | D46: 5375 | F46: =VLOOKUP($K$5,PREÇOS!$A$2:$L$31,8,FALSE) -> 7.98 | G46: =IF($K$7="SIM",VLOOKUP($K$5,'ST BISCOTTI'!$A$1:$J$31,10,FALSE),VLOOKUP($K$5,'ST BISCOTTI'!$A$1:$J$31,9,FALSE)) -> 0 | H46: =SUM(F46:G46) -> 7.98 | I46: =F46*12 -> 95.76 | J46: =(F46+G46)*12 -> 95.76 | K46: =E46*I46 -> 0 | L46: =E46*J46 -> 0 | M46: =VLOOKUP($K$5,PSC!$A$2:$L$31,8,FALSE) -> 13.49
B47: Biscoito Infantil Papapá Biscotti com Maçã e Canela 60g | D47: 5351 | F47: =VLOOKUP($K$5,PREÇOS!$A$2:$L$31,8,FALSE) -> 7.98 | G47: =IF($K$7="SIM",VLOOKUP($K$5,'ST BISCOTTI'!$A$1:$J$31,10,FALSE),VLOOKUP($K$5,'ST BISCOTTI'!$A$1:$J$31,9,FALSE)) -> 0 | H47: =SUM(F47:G47) -> 7.98 | I47: =F47*12 -> 95.76 | J47: =(F47+G47)*12 -> 95.76 | K47: =E47*I47 -> 0 | L47: =E47*J47 -> 0 | M47: =VLOOKUP($K$5,PSC!$A$2:$L$31,8,FALSE) -> 13.49
B48: Biscoito Infantil Papapá Biscotti com Banana e Cacau 60g | D48: 5368 | F48: =VLOOKUP($K$5,PREÇOS!$A$2:$L$31,8,FALSE) -> 7.98 | G48: =IF($K$7="SIM",VLOOKUP($K$5,'ST BISCOTTI'!$A$1:$J$31,10,FALSE),VLOOKUP($K$5,'ST BISCOTTI'!$A$1:$J$31,9,FALSE)) -> 0 | H48: =SUM(F48:G48) -> 7.98 | I48: =F48*12 -> 95.76 | J48: =(F48+G48)*12 -> 95.76 | K48: =E48*I48 -> 0 | L48: =E48*J48 -> 0 | M48: =VLOOKUP($K$5,PSC!$A$2:$L$31,8,FALSE) -> 13.49
B49: Biscoito Infantil Papapá Biscotti Goiaba 60g | D49: 5597 | F49: =VLOOKUP($K$5,PREÇOS!$A$2:$L$31,8,FALSE) -> 7.98 | G49: =IF($K$7="SIM",VLOOKUP($K$5,'ST BISCOTTI'!$A$1:$J$31,10,FALSE),VLOOKUP($K$5,'ST BISCOTTI'!$A$1:$J$31,9,FALSE)) -> 0 | H49: =SUM(F49:G49) -> 7.98 | I49: =F49*12 -> 95.76 | J49: =(F49+G49)*12 -> 95.76 | K49: =E49*I49 -> 0 | L49: =E49*J49 -> 0 | M49: =VLOOKUP($K$5,PSC!$A$2:$L$31,8,FALSE) -> 13.49
B50: Biscoito Infantil Papapá Biscotti com Maracujá e Camomila 60g | D50: 5580 | F50: =VLOOKUP($K$5,PREÇOS!$A$2:$L$31,8,FALSE) -> 7.98 | G50: =IF($K$7="SIM",VLOOKUP($K$5,'ST BISCOTTI'!$A$1:$J$31,10,FALSE),VLOOKUP($K$5,'ST BISCOTTI'!$A$1:$J$31,9,FALSE)) -> 0 | H50: =SUM(F50:G50) -> 7.98 | I50: =F50*12 -> 95.76 | J50: =(F50+G50)*12 -> 95.76 | K50: =E50*I50 -> 0 | L50: =E50*J50 -> 0 | M50: =VLOOKUP($K$5,PSC!$A$2:$L$31,8,FALSE) -> 13.49
B52: Sopinha Papapá Frango Arroz Legumes 240g (2x 120g) | D52: 5610 | F52: =VLOOKUP($K$5,PREÇOS!$A$2:$N$31,14,FALSE) -> 11.704 | G52: 0 | H52: =SUM(F52:G52) -> 11.704 | I52: =F52*6 -> 70.224 | J52: =(F52+G52)*6 -> 70.224 | K52: =E52*I52 -> 0 | L52: =E52*J52 -> 0 | M52: =VLOOKUP($K$5,PSC!$A$2:$N$31,14,FALSE) -> 18.99
B53: Sopinha Papapá Carne Macarrao Legumes 240g (2x 120g) | D53: 5634 | F53: =VLOOKUP($K$5,PREÇOS!$A$2:$N$31,14,FALSE) -> 11.704 | G53: 0 | H53: =SUM(F53:G53) -> 11.704 | I53: =F53*6 -> 70.224 | J53: =(F53+G53)*6 -> 70.224 | K53: =E53*I53 -> 0 | L53: =E53*J53 -> 0 | M53: =VLOOKUP($K$5,PSC!$A$2:$N$31,14,FALSE) -> 18.99
B54: Sopinha Papapá Carne Mandioq Leg 240g (2x 120g) | D54: 5627 | F54: =VLOOKUP($K$5,PREÇOS!$A$2:$N$31,14,FALSE) -> 11.704 | G54: 0 | H54: =SUM(F54:G54) -> 11.704 | I54: =F54*6 -> 70.224 | J54: =(F54+G54)*6 -> 70.224 | K54: =E54*I54 -> 0 | L54: =E54*J54 -> 0 | M54: =VLOOKUP($K$5,PSC!$A$2:$N$31,14,FALSE) -> 18.99
B55: Sopinha Papapá Feijão Carne Leg 240g (2x 120g) | D55: 5606 | F55: =VLOOKUP($K$5,PREÇOS!$A$2:$N$31,14,FALSE) -> 11.704 | G55: 0 | H55: =SUM(F55:G55) -> 11.704 | I55: =F55*6 -> 70.224 | J55: =(F55+G55)*6 -> 70.224 | K55: =E55*I55 -> 0 | L55: =E55*J55 -> 0 | M55: =VLOOKUP($K$5,PSC!$A$2:$N$31,14,FALSE) -> 18.99
E57: Pedido Mínimo: | H57: 800 | J57: VALOR TOTAL PRODUTOS (R$): | M57: =SUM(K17:K22,K14:K15,K11:K12,K24:K26,K28:K29,K31:K32,K34:K36,K38:K44,K46:K50,K52:K55) -> 0
E59: Condição de Pagamento: | J59: VALOR ST (R$): | M59: =M61-M57 -> 0
J61: VALOR TOTAL PEDIDO (R$): | M61: =SUM(L17:L22,L14:L15,L11:L12,L24:L26,L28:L29,L31:L32,L34:L36,L38:L44,L46:L50,L52:L55) -> 0

Sheet DADOS
C1: BABY ROO COMERCIO DE ALIMENTOS EIRELI
C2: CNPJ: 34.282.307.0001-44 | H2: UF: | I2: =TABELA!K5 -> PR
C3: INSC. ESTADUAL: 90821939-25
C4: ENDEREÇO: Rua Grã Nicco, 113 - sala 501, bloco 2 - Mossunguê, Curitiba - PR, 81200-200
B6: =PREÇOS!A1 -> 0325E
B7: Descrição | D7: Código | E7: Embalagem | F7: Validade | G7: NCM | H7: Ean 13 | I7: Dun 14 | J7: Crédito ICMS (%)
B8: Papinha Papapa Carne Arroz Legumes 120g | D8: 5313 | E8: 12 x 120g | F8: 12 meses | G8: 2104.20.00 | H8: 7898969895316 | I8: 17898969895313 | J8: =VLOOKUP($I$2,'ST BISCOITINHOS'!A:B,2,FALSE) -> 0.12
B9: Papinha Papapa Frango Grão Vegetais 120g | D9: 5320 | E9: 12 x 120g | F9: 12 meses | G9: 2104.20.00 | H9: 7898969895323 | I9: 17898969895320 | J9: =VLOOKUP($I$2,'ST BISCOITINHOS'!A:B,2,FALSE) -> 0.12
B11: Papinha Papapa Iogurte Frutas Amarelas e Banana 100g | D11: 5566 | E11: 16 x 100g | F11: 15 meses | G11: 2104.20.00 | H11: 7898969895569 | I11: 27898969895563 | J11: =VLOOKUP($I$2,'ST BISCOITINHOS'!A:B,2,FALSE) -> 0.12
B12: Papinha Papapa Iogurte Frutas Vermelhas e Banana 100g | D12: 5573 | E12: 16 x 100g | F12: 15 meses | G12: 2104.20.00 | H12: 7898969895576 | I12: 27898969895570 | J12: =VLOOKUP($I$2,'ST BISCOITINHOS'!A:B,2,FALSE) -> 0.12
B14: Papinha Papapá Org Maçã Ameixa 100g | D14: 17898994908729 | E14: 12 x 100g | F14: 16 meses | G14: 2104.20.00 | H14: 7898994908722 | I14: 17898994908729 | J14: =VLOOKUP($I$2,'ST BISCOITINHOS'!A:B,2,FALSE) -> 0.12
B15: Papinha Papapá Org Banana Mirtilo Quinoa 100g | D15: 17898994908736 | E15: 12 x 100g | F15: 16 meses | G15: 2104.20.00 | H15: 7898994908739 | I15: 17898994908736 | J15: =VLOOKUP($I$2,'ST BISCOITINHOS'!A:B,2,FALSE) -> 0.12
B16: Papinha Papapá Org Manga 100g | D16: 17898994908712 | E16: 12 x 100g | F16: 16 meses | G16: 2104.20.00 | H16: 7898994908715 | I16: 17898994908712 | J16: =VLOOKUP($I$2,'ST BISCOITINHOS'!A:B,2,FALSE) -> 0.12
B17: Papinha Papapá Org Pera Espinafre Abobrinha 100g | D17: 17898994908750 | E17: 12 x 100g | F17: 16 meses | G17: 2104.20.00 | H17: 7898994908753 | I17: 17898994908750 | J17: =VLOOKUP($I$2,'ST BISCOITINHOS'!A:B,2,FALSE) -> 0.12
B18: Papinha Papapá Org Maçã B. Doce Cenoura 100g | D18: 27898994908757 | E18: 12 x 100g | F18: 16 meses | G18: 2104.20.00 | H18: 7898994908746 | I18: 27898994908757 | J18: =VLOOKUP($I$2,'ST BISCOITINHOS'!A:B,2,FALSE) -> 0.12
B19: Papinha Papapá Org Morango Maçã 100g | D19: 5306 | E19: 12 x 100g | F19: 16 meses | G19: 2104.20.00 | H19: 7898969895309 | I19: 17898969895306 | J19: =VLOOKUP($I$2,'ST BISCOITINHOS'!A:B,2,FALSE) -> 0.12
B21: Biscoito inf Papapá Palitinho de Vegetais org. Beterraba 20g | D21: 5085 | E21: 16 x 20g | F21: 9 meses | G21: 1904.10.00 | H21: 7898969895088 | I21: 17898969895085 | J21: =VLOOKUP($I$2,'ST PALITINHOS'!A:B,2,FALSE) -> 0.12
B22: Biscoito inf Papapá Palitinho de Vegetais org. Cenoura 20g | D22: 5078 | E22: 16 x 20g | F22: 9 meses | G22: 1904.10.00 | H22: 7898969895071 | I22: 17898969895078 | J22: =VLOOKUP($I$2,'ST PALITINHOS'!A:B,2,FALSE) -> 0.12
B23: Biscoito inf Papapá Palitinho de Vegetais org. Tomate/Manjericão 20g | D23: 5061 | E23: 16 x 20g | F23: 9 meses | G23: 1904.10.00 | H23: 7898969895064 | I23: 17898969895061 | J23: =VLOOKUP($I$2,'ST PALITINHOS'!A:B,2,FALSE) -> 0.12
B25: Biscoito Inf Papapá dent. Maçã e Abóbora 36g | D25: 8774 | E25: 12 x 36g | F25: 15 meses | G25: 1905.90.20 | H25: 7898994908777 | I25: 17898994908774 | J25: =VLOOKUP($I$2,'ST BISCOITINHOS'!A:B,2,FALSE) -> 0.12
B26: Biscoito Inf Papapá dent Vegetais 36g | D26: 8767 | E26: 12 x 36g | F26: 15 meses | G26: 1905.90.20 | H26: 7898994908760 | I26: 17898994908767 | J26: =VLOOKUP($I$2,'ST BISCOITINHOS'!A:B,2,FALSE) -> 0.12
B28: Macarrao Inf Papapá m. Elbow Quinoa 200g | D28: 5290 | E28: 12 x 200g | F28: 14 meses | G28: 19.02.19.00 | H28: 7898969895293 | I28: 17898969895293 | J28: =VLOOKUP($I$2,'ST PAPAPASTA'!A:B,2,FALSE) -> 0.12
B29: Macarrao Inf Papapá m. Fusilli Vegetais 200g | D29: 5283 | E29: 12 x 200g | F29: 14 meses | G29: 19.02.19.00 | H29: 7898969895286 | I29: 17898969895286 | J29: =VLOOKUP($I$2,'ST PAPAPASTA'!A:B,2,FALSE) -> 0.12
B31: Sopinha Papapá org Lentinha Carne Legumes 180g | D31: 5276 | E31: 6 x 180g | F31: 16 meses | G31: 2104.20.00 | H31: 7898969895279 | I31: 17898969895276 | J31: =VLOOKUP($I$2,'ST PAPAPASTA'!A:B,2,FALSE) -> 0.12
B32: Risotinho Papapá org Arroz quinoa frango 180g | D32: 5269 | E32: 6 x 180g | F32: 16 meses | G32: 2104.20.00 | H32: 7898969895262 | I32: 17898969895269 | J32: =VLOOKUP($I$2,'ST PAPAPASTA'!A:B,2,FALSE) -> 0.12
B33: Caseirinho Papapá org Arroz feijão carne leg. 180g | D33: 5252 | E33: 6 x 180g | F33: 16 meses | G33: 2104.20.00 | H33: 7898969895255 | I33: 17898969895252 | J33: =VLOOKUP($I$2,'ST PAPAPASTA'!A:B,2,FALSE) -> 0.12
B35: Cereal Infantil Papapá Aveia - Morango e Beterraba 170g caixa | D35: 3344 | E35: 12 x 170g | F35: 12 meses | G35: 19.01.10.30 | H35: 7898969895330 | I35: 17898969895337 | J35: =VLOOKUP($I$2,'ST CEREAL'!A:B,2,FALSE) -> 0.12
B36: Cereal Infantil Papapá Aveia - Banana e Ameixa 170g caixa | D36: 3343 | E36: 12 x 170g | F36: 12 meses | G36: 19.01.10.30 | H36: 7898969895347 | I36: 17898969895344 | J36: =VLOOKUP($I$2,'ST CEREAL'!A:B,2,FALSE) -> 0.12
B37: Cereal Infantil Papapá Aveia - Multicereais 170g caixa | D37: 5382 | E37: 12 x 170g | F37: 12 meses | G37: 19.01.10.30 | H37: 7898969895385 | I37: 17898969895382 | J37: =VLOOKUP($I$2,'ST CEREAL'!A:B,2,FALSE) -> 0.12
B38: Cereal Infantil Papapá Aveia - Morango e Beterraba sache 170g | D38: 5402 | E38: 12 x 170g | F38: 12 meses | G38: 19.01.10.30 | H38: 7898969895408 | I38: 27898969895402 | J38: =VLOOKUP($I$2,'ST CEREAL SABOR POUCH 170'!A:B,2,FALSE) -> 0.12
B39: Cereal Infantil Papapá Aveia - Banana e Ameixa sache 170g | D39: 5419 | E39: 12 x 170g | F39: 12 meses | G39: 19.01.10.30 | H39: 7898969895415 | I39: 27898969895419 | J39: =VLOOKUP($I$2,'ST CEREAL SABOR POUCH 170'!A:B,2,FALSE) -> 0.12
B40: Cereal Infantil Papapá Aveia - Multicereais sache 170g | D40: 5429 | E40: 12 x 170g | F40: 12 meses | G40: 19.01.10.30 | H40: 7898969895422 | I40: 17898969895429 | J40: =VLOOKUP($I$2,'ST MULTI 170 POUCH'!A:B,2,FALSE) -> 0.12
B41: Cereal Infantil Papapá Aveia - Multicereais sache 500g | D41: 5399 | E41: 12 x 500g | F41: 12 meses | G41: 19.01.10.30 | H41: 7898969895392 | I41: 17898969895399 | J41: =VLOOKUP($I$2,'ST MULTI 500 POUCH'!A:B,2,FALSE) -> 0.12
B43: Biscoito Infantil Papapá Biscotti com Laranja e Cenoura 60g | D43: 5375 | E43: 12 x 60g | F43: 10 meses | G43: 1905.90.20 | H43: 7898969895378 | I43: 17898969895375 | J43: =VLOOKUP($I$2,'ST BISCOTTI'!A:B,2,FALSE) -> 0.12
B44: Biscoito Infantil Papapá Biscotti com Maçã e Canela 60g | D44: 5351 | E44: 12 x 60g | F44: 10 meses | G44: 1905.90.20 | H44: 7898969895354 | I44: 17898969895351 | J44: =VLOOKUP($I$2,'ST BISCOTTI'!A:B,2,FALSE) -> 0.12
B45: Biscoito Infantil Papapá Biscotti com Banana e Cacau 60g | D45: 5368 | E45: 12 x 60g | F45: 10 meses | G45: 1905.90.20 | H45: 7898969895361 | I45: 17898969895368 | J45: =VLOOKUP($I$2,'ST BISCOTTI'!A:B,2,FALSE) -> 0.12
B46: Biscoito Infantil Papapá Biscotti Goiaba 60g | D46: 5597 | E46: 12 x 60g | F46: 10 meses | G46: 1905.90.20 | H46: 7898969895590 | I46: 17898969895597 | J46: =VLOOKUP($I$2,'ST BISCOTTI'!A:B,2,FALSE) -> 0.12
B47: Biscoito Infantil Papapá Biscotti com Maracujá e Camomila 60g | D47: 5580 | E47: 12 x 60g | F47: 10 meses | G47: 1905.90.20 | H47: 7898969895583 | I47: 17898969895580 | J47: =VLOOKUP($I$2,'ST BISCOTTI'!A:B,2,FALSE) -> 0.12
B49: Sopinha Papapá Frango Arroz Legumes 240g (2x 120g) | D49: 5610 | E49: 6 x 240g | F49: 12 meses | G49: 2104.20.00 | H49: 7898969895613 | I49: 17898969895610 | J49: =VLOOKUP($I$2,'[2]ST BISCOTTI'!A:B,2,FALSE) -> 0.12
B50: Sopinha Papapá Carne Macarrao Legumes 240g (2x 120g) | D50: 5634 | E50: 6 x 240g | F50: 12 meses | G50: 2104.20.00 | H50: 7898969895637 | I50: 17898969895634 | J50: =VLOOKUP($I$2,'[2]ST BISCOTTI'!A:B,2,FALSE) -> 0.12
B51: Sopinha Papapá Carne Mandioq Leg 240g (2x 120g) | D51: 5627 | E51: 6 x 240g | F51: 12 meses | G51: 2104.20.00 | H51: 7898969895620 | I51: 17898969895627 | J51: =VLOOKUP($I$2,'[2]ST BISCOTTI'!A:B,2,FALSE) -> 0.12
B52: Sopinha Papapá Feijão Carne Leg 240g (2x 120g) | D52: 5603 | E52: 6 x 240g | F52: 12 meses | G52: 2104.20.00 | H52: 7898969895606 | I52: 17898969895603 | J52: =VLOOKUP($I$2,'[2]ST BISCOTTI'!A:B,2,FALSE) -> 0.12

Sheet Planilha1
C2: SIM
C3: NÃO

Sheet ST BISCOITINHOS
A1: Estado | B1: Aliquota interestadual | C1: Aliquota interna | D1: MVA (normal) | E1: MVA (simples) | F1: Ajustada (normal) | G1: Ajustada (simples) | H1: Preço | I1: ST Normal | J1: ST Simples
A2: AC | B2: 0.04 | C2: 0.04 | H2: =PREÇOS!D3 -> 10.8965 | I2: =IF(F2=0,,H2*(1+F2)*C2-(H2*B2)) -> 0 | J2: =IF(G2=0,IF(F2=0,,H2*(1+F2)*C2-(H2*B2)),H2*(1+G2)*C2-(H2*B2)) -> 0
A3: AL | B3: 0.04 | C3: 0.2 | D3: 0.3 | F3: 0.56 | H3: =PREÇOS!D4 -> 10.8965 | I3: =IF(F3=0,,H3*(1+F3)*C3-(H3*B3)) -> 2.963848 | J3: =IF(G3=0,IF(F3=0,,H3*(1+F3)*C3-(H3*B3)),H3*(1+G3)*C3-(H3*B3)) -> 2.963848
A4: AM | B4: 0.04 | C4: 0.04 | H4: =PREÇOS!D5 -> 10.8965 | I4: =IF(F4=0,,H4*(1+F4)*C4-(H4*B4)) -> 0 | J4: =IF(G4=0,IF(F4=0,,H4*(1+F4)*C4-(H4*B4)),H4*(1+G4)*C4-(H4*B4)) -> 0
A5: AP | B5: 0.04 | C5: 0.18 | D5: 0.34 | F5: 0.5688 | H5: =PREÇOS!D6 -> 10.8965 | I5: =IF(F5=0,,H5*(1+F5)*C5-(H5*B5)) -> 2.6411373 | J5: =IF(G5=0,IF(F5=0,,H5*(1+F5)*C5-(H5*B5)),H5*(1+G5)*C5-(H5*B5)) -> 2.6411373
A6: BA | B6: 0.04 | C6: 0.04 | H6: =PREÇOS!D7 -> 10.8965 | I6: =IF(F6=0,,H6*(1+F6)*C6-(H6*B6)) -> 0 | J6: =IF(G6=0,IF(F6=0,,H6*(1+F6)*C6-(H6*B6)),H6*(1+G6)*C6-(H6*B6)) -> 0
A7: CE | B7: 0.04 | C7: 0.04 | H7: =PREÇOS!D8 -> 10.8965 | I7: =IF(F7=0,,H7*(1+F7)*C7-(H7*B7)) -> 0 | J7: =IF(G7=0,IF(F7=0,,H7*(1+F7)*C7-(H7*B7)),H7*(1+G7)*C7-(H7*B7)) -> 0
A8: DF | B8: 0.04 | C8: 0.04 | H8: =PREÇOS!D9 -> 10.8965 | I8: =IF(F8=0,,H8*(1+F8)*C8-(H8*B8)) -> 0 | J8: =IF(G8=0,IF(F8=0,,H8*(1+F8)*C8-(H8*B8)),H8*(1+G8)*C8-(H8*B8)) -> 0
A9: ES | B9: 0.04 | C9: 0.04 | H9: =PREÇOS!D10 -> 10.8965 | I9: =IF(F9=0,,H9*(1+F9)*C9-(H9*B9)) -> 0 | J9: =IF(G9=0,IF(F9=0,,H9*(1+F9)*C9-(H9*B9)),H9*(1+G9)*C9-(H9*B9)) -> 0
A10: GO | B10: 0.04 | C10: 0.04 | H10: =PREÇOS!D11 -> 10.8965 | I10: =IF(F10=0,,H10*(1+F10)*C10-(H10*B10)) -> 0 | J10: =IF(G10=0,IF(F10=0,,H10*(1+F10)*C10-(H10*B10)),H10*(1+G10)*C10-(H10*B10)) -> 0
A11: MA | B11: 0.04 | C11: 0.04 | H11: =PREÇOS!D12 -> 10.8965 | I11: =IF(F11=0,,H11*(1+F11)*C11-(H11*B11)) -> 0 | J11: =IF(G11=0,IF(F11=0,,H11*(1+F11)*C11-(H11*B11)),H11*(1+G11)*C11-(H11*B11)) -> 0
A12: MG | B12: 0.04 | C12: 0.18 | D12: 0.25 | F12: 0.3636 | H12: =PREÇOS!D13 -> 10.8965 | I12: =IF(F12=0,,H12*(1+F12)*C12-(H12*B12)) -> 2.2386641 | J12: =IF(G12=0,IF(F12=0,,H12*(1+F12)*C12-(H12*B12)),H12*(1+G12)*C12-(H12*B12)) -> 2.2386641
A13: MS | B13: 0.04 | C13: 0.04 | H13: =PREÇOS!D14 -> 10.8965 | I13: =IF(F13=0,,H13*(1+F13)*C13-(H13*B13)) -> 0 | J13: =IF(G13=0,IF(F13=0,,H13*(1+F13)*C13-(H13*B13)),H13*(1+G13)*C13-(H13*B13)) -> 0
A14: MT | B14: 0.04 | C14: 0.04 | H14: =PREÇOS!D15 -> 10.8965 | I14: =IF(F14=0,,H14*(1+F14)*C14-(H14*B14)) -> 0 | J14: =IF(G14=0,IF(F14=0,,H14*(1+F14)*C14-(H14*B14)),H14*(1+G14)*C14-(H14*B14)) -> 0
A15: PA | B15: 0.04 | C15: 0.04 | H15: =PREÇOS!D16 -> 10.8965 | I15: =IF(F15=0,,H15*(1+F15)*C15-(H15*B15)) -> 0 | J15: =IF(G15=0,IF(F15=0,,H15*(1+F15)*C15-(H15*B15)),H15*(1+G15)*C15-(H15*B15)) -> 0
A16: PB | B16: 0.04 | C16: 0.04 | H16: =PREÇOS!D17 -> 10.8965 | I16: =IF(F16=0,,H16*(1+F16)*C16-(H16*B16)) -> 0 | J16: =IF(G16=0,IF(F16=0,,H16*(1+F16)*C16-(H16*B16)),H16*(1+G16)*C16-(H16*B16)) -> 0
A17: PE | B17: 0.04 | C17: 0.04 | H17: =PREÇOS!D18 -> 10.8965 | I17: =IF(F17=0,,H17*(1+F17)*C17-(H17*B17)) -> 0 | J17: =IF(G17=0,IF(F17=0,,H17*(1+F17)*C17-(H17*B17)),H17*(1+G17)*C17-(H17*B17)) -> 0
A18: PI | B18: 0.04 | C18: 0.04 | H18: =PREÇOS!D19 -> 10.8965 | I18: =IF(F18=0,,H18*(1+F18)*C18-(H18*B18)) -> 0 | J18: =IF(G18=0,IF(F18=0,,H18*(1+F18)*C18-(H18*B18)),H18*(1+G18)*C18-(H18*B18)) -> 0
A19: PR | B19: 0.12 | C19: 0.12 | H19: =PREÇOS!D20 -> 11.951 | I19: =IF(F19=0,,H19*(1+F19)*C19-(H19*B19)) -> 0 | J19: =IF(G19=0,IF(F19=0,,H19*(1+F19)*C19-(H19*B19)),H19*(1+G19)*C19-(H19*B19)) -> 0
A20: RJ | B20: 0.04 | C20: 0.22 | D20: 0.352 | F20: 0.664 | H20: =PREÇOS!D21 -> 10.8965 | I20: =IF(F20=0,,H20*(1+F20)*C20-(H20*B20)) -> 3.5531307 | J20: =IF(G20=0,IF(F20=0,,H20*(1+F20)*C20-(H20*B20)),H20*(1+G20)*C20-(H20*B20)) -> 3.5531307
A21: RN | B21: 0.04 | C21: 0.04 | H21: =PREÇOS!D22 -> 10.8965 | I21: =IF(F21=0,,H21*(1+F21)*C21-(H21*B21)) -> 0 | J21: =IF(G21=0,IF(F21=0,,H21*(1+F21)*C21-(H21*B21)),H21*(1+G21)*C21-(H21*B21)) -> 0
A22: RO | B22: 0.04 | C22: 0.04 | H22: =PREÇOS!D23 -> 10.8965 | I22: =IF(F22=0,,H22*(1+F22)*C22-(H22*B22)) -> 0 | J22: =IF(G22=0,IF(F22=0,,H22*(1+F22)*C22-(H22*B22)),H22*(1+G22)*C22-(H22*B22)) -> 0
A23: RR | B23: 0.04 | C23: 0.04 | H23: =PREÇOS!D24 -> 10.8965 | I23: =IF(F23=0,,H23*(1+F23)*C23-(H23*B23)) -> 0 | J23: =IF(G23=0,IF(F23=0,,H23*(1+F23)*C23-(H23*B23)),H23*(1+G23)*C23-(H23*B23)) -> 0
A24: RS | B24: 0.04 | C24: 0.04 | H24: =PREÇOS!D25 -> 10.8965 | I24: =IF(F24=0,,H24*(1+F24)*C24-(H24*B24)) -> 0 | J24: =IF(G24=0,IF(F24=0,,H24*(1+F24)*C24-(H24*B24)),H24*(1+G24)*C24-(H24*B24)) -> 0
A25: SC | B25: 0.04 | C25: 0.04 | H25: =PREÇOS!D26 -> 10.8965 | I25: =IF(F25=0,,H25*(1+F25)*C25-(H25*B25)) -> 0 | J25: =IF(G25=0,IF(F25=0,,H25*(1+F25)*C25-(H25*B25)),H25*(1+G25)*C25-(H25*B25)) -> 0
A26: SE | B26: 0.04 | C26: 0.04 | H26: =PREÇOS!D27 -> 10.8965 | I26: =IF(F26=0,,H26*(1+F26)*C26-(H26*B26)) -> 0 | J26: =IF(G26=0,IF(F26=0,,H26*(1+F26)*C26-(H26*B26)),H26*(1+G26)*C26-(H26*B26)) -> 0
A27: SP | B27: 0.04 | C27: 0.18 | D27: 0.4832 | F27: 0.618 | H27: =PREÇOS!D28 -> 10.8965 | I27: =IF(F27=0,,H27*(1+F27)*C27-(H27*B27)) -> 2.7376367 | J27: =IF(G27=0,IF(F27=0,,H27*(1+F27)*C27-(H27*B27)),H27*(1+G27)*C27-(H27*B27)) -> 2.7376367
A28: SP/Atacado | B28: =B27 -> 0.04 | C28: =C27 -> 0.18 | D28: =D27 -> 0.4832 | E28: =E27 -> 0 | F28: =F27 -> 0.618 | G28: =G27 -> 0 | H28: =PREÇOS!D29 -> 10.8965 | I28: =IF(F28=0,,H28*(1+F28)*C28-(H28*B28)) -> 2.7376367 | J28: =IF(G28=0,IF(F28=0,,H28*(1+F28)*C28-(H28*B28)),H28*(1+G28)*C28-(H28*B28)) -> 2.7376367
A29: TO | B29: 0.04 | C29: 0.04 | H29: =PREÇOS!D30 -> 10.8965 | I29: =IF(F29=0,,H29*(1+F29)*C29-(H29*B29)) -> 0 | J29: =IF(G29=0,IF(F29=0,,H29*(1+F29)*C29-(H29*B29)),H29*(1+G29)*C29-(H29*B29)) -> 0
A30: EX | H30: =PREÇOS!D31 -> 0 | I30: =IF(F30=0,,H30*(1+F30)*C30-(H30*B30)) -> 0 | J30: =IF(G30=0,IF(F30=0,,H30*(1+F30)*C30-(H30*B30)),H30*(1+G30)*C30-(H30*B30)) -> 0

Sheet ST PAPAPASTA
A1: Estado | B1: Aliquota interestadual | C1: Aliquota interna | D1: MVA (normal) | E1: MVA (simples) | F1: Ajustada (normal) | G1: Ajustada (simples) | H1: Preço | I1: ST Normal | J1: ST Simples
A2: AC | B2: 0.07 | C2: 0.07 | H2: =PREÇOS!E3 -> 7.5335 | I2: =IF(F2=0,,H2*(1+F2)*C2-(H2*B2)) -> 0 | J2: =IF(G2=0,IF(F2=0,,H2*(1+F2)*C2-(H2*B2)),H2*(1+G2)*C2-(H2*B2)) -> 0
A3: AL | B3: 0.07 | C3: 0.19 | D3: 0.2 | F3: 0.361 | H3: =PREÇOS!E4 -> 7.5335 | I3: =IF(F3=0,,H3*(1+F3)*C3-(H3*B3)) -> 1.4207428 | J3: =IF(G3=0,IF(F3=0,,H3*(1+F3)*C3-(H3*B3)),H3*(1+G3)*C3-(H3*B3)) -> 1.4207428
A4: AM | B4: 0.07 | C4: 0.07 | H4: =PREÇOS!E5 -> 7.5335 | I4: =IF(F4=0,,H4*(1+F4)*C4-(H4*B4)) -> 0 | J4: =IF(G4=0,IF(F4=0,,H4*(1+F4)*C4-(H4*B4)),H4*(1+G4)*C4-(H4*B4)) -> 0
A5: AP | B5: 0.07 | C5: 0.18 | D5: 0.38 | F5: 0.5651 | H5: =PREÇOS!E6 -> 7.5335 | I5: =IF(F5=0,,H5*(1+F5)*C5-(H5*B5)) -> 1.5949776 | J5: =IF(G5=0,IF(F5=0,,H5*(1+F5)*C5-(H5*B5)),H5*(1+G5)*C5-(H5*B5)) -> 1.5949776
A6: BA | B6: 0.07 | C6: 0.07 | H6: =PREÇOS!E7 -> 7.5335 | I6: =IF(F6=0,,H6*(1+F6)*C6-(H6*B6)) -> 0 | J6: =IF(G6=0,IF(F6=0,,H6*(1+F6)*C6-(H6*B6)),H6*(1+G6)*C6-(H6*B6)) -> 0
A7: CE | B7: 0.07 | C7: 0.07 | H7: =PREÇOS!E8 -> 7.5335 | I7: =IF(F7=0,,H7*(1+F7)*C7-(H7*B7)) -> 0 | J7: =IF(G7=0,IF(F7=0,,H7*(1+F7)*C7-(H7*B7)),H7*(1+G7)*C7-(H7*B7)) -> 0
A8: DF | B8: 0.07 | C8: 0.07 | H8: =PREÇOS!E9 -> 7.5335 | I8: =IF(F8=0,,H8*(1+F8)*C8-(H8*B8)) -> 0 | J8: =IF(G8=0,IF(F8=0,,H8*(1+F8)*C8-(H8*B8)),H8*(1+G8)*C8-(H8*B8)) -> 0
A9: ES | B9: 0.07 | C9: 0.07 | H9: =PREÇOS!E10 -> 7.5335 | I9: =IF(F9=0,,H9*(1+F9)*C9-(H9*B9)) -> 0 | J9: =IF(G9=0,IF(F9=0,,H9*(1+F9)*C9-(H9*B9)),H9*(1+G9)*C9-(H9*B9)) -> 0
A10: GO | B10: 0.07 | C10: 0.07 | H10: =PREÇOS!E11 -> 7.5335 | I10: =IF(F10=0,,H10*(1+F10)*C10-(H10*B10)) -> 0 | J10: =IF(G10=0,IF(F10=0,,H10*(1+F10)*C10-(H10*B10)),H10*(1+G10)*C10-(H10*B10)) -> 0
A11: MA | B11: 0.07 | C11: 0.07 | H11: =PREÇOS!E12 -> 7.5335 | I11: =IF(F11=0,,H11*(1+F11)*C11-(H11*B11)) -> 0 | J11: =IF(G11=0,IF(F11=0,,H11*(1+F11)*C11-(H11*B11)),H11*(1+G11)*C11-(H11*B11)) -> 0
A12: MG | B12: 0.12 | C12: 0.18 | D12: 0.35 | F12: 0.35 | H12: =PREÇOS!E13 -> 8.0275 | I12: =IF(F12=0,,H12*(1+F12)*C12-(H12*B12)) -> 0.9873825 | J12: =IF(G12=0,IF(F12=0,,H12*(1+F12)*C12-(H12*B12)),H12*(1+G12)*C12-(H12*B12)) -> 0.9873825
A13: MS | B13: 0.07 | C13: 0.07 | H13: =PREÇOS!E14 -> 7.5335 | I13: =IF(F13=0,,H13*(1+F13)*C13-(H13*B13)) -> 0 | J13: =IF(G13=0,IF(F13=0,,H13*(1+F13)*C13-(H13*B13)),H13*(1+G13)*C13-(H13*B13)) -> 0
A14: MT | B14: 0.07 | C14: 0.17 | D14: 0.3545 | F14: 0.3545 | H14: =PREÇOS!E15 -> 7.5335 | I14: =IF(F14=0,,H14*(1+F14)*C14-(H14*B14)) -> 1.2073564 | J14: =IF(G14=0,IF(F14=0,,H14*(1+F14)*C14-(H14*B14)),H14*(1+G14)*C14-(H14*B14)) -> 1.2073564
A15: PA | B15: 0.07 | C15: 0.07 | H15: =PREÇOS!E16 -> 7.5335 | I15: =IF(F15=0,,H15*(1+F15)*C15-(H15*B15)) -> 0 | J15: =IF(G15=0,IF(F15=0,,H15*(1+F15)*C15-(H15*B15)),H15*(1+G15)*C15-(H15*B15)) -> 0
A16: PB | B16: 0.07 | C16: 0.07 | H16: =PREÇOS!E17 -> 7.5335 | I16: =IF(F16=0,,H16*(1+F16)*C16-(H16*B16)) -> 0 | J16: =IF(G16=0,IF(F16=0,,H16*(1+F16)*C16-(H16*B16)),H16*(1+G16)*C16-(H16*B16)) -> 0
A17: PE | B17: 0.07 | C17: 0.07 | H17: =PREÇOS!E18 -> 7.5335 | I17: =IF(F17=0,,H17*(1+F17)*C17-(H17*B17)) -> 0 | J17: =IF(G17=0,IF(F17=0,,H17*(1+F17)*C17-(H17*B17)),H17*(1+G17)*C17-(H17*B17)) -> 0
A18: PI | B18: 0.07 | C18: 0.07 | H18: =PREÇOS!E19 -> 7.5335 | I18: =IF(F18=0,,H18*(1+F18)*C18-(H18*B18)) -> 0 | J18: =IF(G18=0,IF(F18=0,,H18*(1+F18)*C18-(H18*B18)),H18*(1+G18)*C18-(H18*B18)) -> 0
A19: PR | B19: 0.12 | C19: 0.12 | H19: =PREÇOS!E20 -> 8.0275 | I19: =IF(F19=0,,H19*(1+F19)*C19-(H19*B19)) -> 0 | J19: =IF(G19=0,IF(F19=0,,H19*(1+F19)*C19-(H19*B19)),H19*(1+G19)*C19-(H19*B19)) -> 0
A20: RJ | B20: 0.12 | C20: 0.12 | H20: =PREÇOS!E21 -> 8.0275 | I20: =IF(F20=0,,H20*(1+F20)*C20-(H20*B20)) -> 0 | J20: =IF(G20=0,IF(F20=0,,H20*(1+F20)*C20-(H20*B20)),H20*(1+G20)*C20-(H20*B20)) -> 0
A21: RN | B21: 0.07 | C21: 0.07 | H21: =PREÇOS!E22 -> 7.5335 | I21: =IF(F21=0,,H21*(1+F21)*C21-(H21*B21)) -> 0 | J21: =IF(G21=0,IF(F21=0,,H21*(1+F21)*C21-(H21*B21)),H21*(1+G21)*C21-(H21*B21)) -> 0
A22: RO | B22: 0.07 | C22: 0.07 | H22: =PREÇOS!E23 -> 7.5335 | I22: =IF(F22=0,,H22*(1+F22)*C22-(H22*B22)) -> 0 | J22: =IF(G22=0,IF(F22=0,,H22*(1+F22)*C22-(H22*B22)),H22*(1+G22)*C22-(H22*B22)) -> 0
A23: RR | B23: 0.07 | C23: 0.07 | H23: =PREÇOS!E24 -> 7.5335 | I23: =IF(F23=0,,H23*(1+F23)*C23-(H23*B23)) -> 0 | J23: =IF(G23=0,IF(F23=0,,H23*(1+F23)*C23-(H23*B23)),H23*(1+G23)*C23-(H23*B23)) -> 0
A24: RS | B24: 0.12 | C24: 0.12 | H24: =PREÇOS!E25 -> 8.0275 | I24: =IF(F24=0,,H24*(1+F24)*C24-(H24*B24)) -> 0 | J24: =IF(G24=0,IF(F24=0,,H24*(1+F24)*C24-(H24*B24)),H24*(1+G24)*C24-(H24*B24)) -> 0
A25: SC | B25: 0.12 | C25: 0.12 | H25: =PREÇOS!E26 -> 8.0275 | I25: =IF(F25=0,,H25*(1+F25)*C25-(H25*B25)) -> 0 | J25: =IF(G25=0,IF(F25=0,,H25*(1+F25)*C25-(H25*B25)),H25*(1+G25)*C25-(H25*B25)) -> 0
A26: SE | B26: 0.07 | C26: 0.07 | H26: =PREÇOS!E27 -> 7.5335 | I26: =IF(F26=0,,H26*(1+F26)*C26-(H26*B26)) -> 0 | J26: =IF(G26=0,IF(F26=0,,H26*(1+F26)*C26-(H26*B26)),H26*(1+G26)*C26-(H26*B26)) -> 0
A27: SP | B27: 0.12 | C27: 0.12 | H27: =PREÇOS!E28 -> 8.0275 | I27: =IF(F27=0,,H27*(1+F27)*C27-(H27*B27)) -> 0 | J27: =IF(G27=0,IF(F27=0,,H27*(1+F27)*C27-(H27*B27)),H27*(1+G27)*C27-(H27*B27)) -> 0
A28: SP/Atacado | B28: =B27 -> 0.12 | C28: =C27 -> 0.12 | D28: =D27 -> 0 | E28: =E27 -> 0 | F28: =F27 -> 0 | G28: =G27 -> 0 | H28: =PREÇOS!E29 -> 8.0275 | I28: =IF(F28=0,,H28*(1+F28)*C28-(H28*B28)) -> 0 | J28: =IF(G28=0,IF(F28=0,,H28*(1+F28)*C28-(H28*B28)),H28*(1+G28)*C28-(H28*B28)) -> 0
A29: TO | B29: 0.07 | C29: 0.07 | H29: =PREÇOS!E30 -> 7.5335 | I29: =IF(F29=0,,H29*(1+F29)*C29-(H29*B29)) -> 0 | J29: =IF(G29=0,IF(F29=0,,H29*(1+F29)*C29-(H29*B29)),H29*(1+G29)*C29-(H29*B29)) -> 0
A30: EX | H30: =PREÇOS!E31 -> 0 | I30: =IF(F30=0,,H30*(1+F30)*C30-(H30*B30)) -> 0 | J30: =IF(G30=0,IF(F30=0,,H30*(1+F30)*C30-(H30*B30)),H30*(1+G30)*C30-(H30*B30)) -> 0

Sheet ST PALITINHOS
A1: Estado | B1: Aliquota interestadual | C1: Aliquota interna | D1: MVA (normal) | E1: MVA (simples) | F1: Ajustada (normal) | G1: Ajustada (simples) | H1: Preço | I1: ST Normal | J1: ST Simples
A2: AC | B2: 0.07 | C2: 0.07 | H2: =PREÇOS!C3 -> 3.3915 | I2: =IF(F2=0,,H2*(1+F2)*C2-(H2*B2)) -> 0 | J2: =IF(G2=0,IF(F2=0,,H2*(1+F2)*C2-(H2*B2)),H2*(1+G2)*C2-(H2*B2)) -> 0
A3: AL | B3: 0.07 | C3: 0.19 | D3: 0.5432 | F3: 0.794 | H3: =PREÇOS!C4 -> 3.3915 | I3: =IF(F3=0,,H3*(1+F3)*C3-(H3*B3)) -> 0.91862169 | J3: =IF(G3=0,IF(F3=0,,H3*(1+F3)*C3-(H3*B3)),H3*(1+G3)*C3-(H3*B3)) -> 0.91862169
A4: AM | B4: 0.07 | C4: 0.18 | H4: =PREÇOS!C5 -> 3.3915 | I4: =IF(F4=0,,H4*(1+F4)*C4-(H4*B4)) -> 0 | J4: =IF(G4=0,IF(F4=0,,H4*(1+F4)*C4-(H4*B4)),H4*(1+G4)*C4-(H4*B4)) -> 0
A5: AP | B5: 0.07 | C5: 0.18 | D5: 0.41 | F5: 0.5991 | H5: =PREÇOS!C6 -> 3.3915 | I5: =IF(F5=0,,H5*(1+F5)*C5-(H5*B5)) -> 0.73879758 | J5: =IF(G5=0,IF(F5=0,,H5*(1+F5)*C5-(H5*B5)),H5*(1+G5)*C5-(H5*B5)) -> 0.73879758
A6: BA | B6: 0.07 | C6: 0.07 | H6: =PREÇOS!C7 -> 3.3915 | I6: =IF(F6=0,,H6*(1+F6)*C6-(H6*B6)) -> 0 | J6: =IF(G6=0,IF(F6=0,,H6*(1+F6)*C6-(H6*B6)),H6*(1+G6)*C6-(H6*B6)) -> 0
A7: CE | B7: 0.07 | C7: 0.07 | H7: =PREÇOS!C8 -> 3.3915 | I7: =IF(F7=0,,H7*(1+F7)*C7-(H7*B7)) -> 0 | J7: =IF(G7=0,IF(F7=0,,H7*(1+F7)*C7-(H7*B7)),H7*(1+G7)*C7-(H7*B7)) -> 0
A8: DF | B8: 0.07 | C8: 0.07 | H8: =PREÇOS!C9 -> 3.3915 | I8: =IF(F8=0,,H8*(1+F8)*C8-(H8*B8)) -> 0 | J8: =IF(G8=0,IF(F8=0,,H8*(1+F8)*C8-(H8*B8)),H8*(1+G8)*C8-(H8*B8)) -> 0
A9: ES | B9: 0.07 | C9: 0.07 | H9: =PREÇOS!C10 -> 3.3915 | I9: =IF(F9=0,,H9*(1+F9)*C9-(H9*B9)) -> 0 | J9: =IF(G9=0,IF(F9=0,,H9*(1+F9)*C9-(H9*B9)),H9*(1+G9)*C9-(H9*B9)) -> 0
A10: GO | B10: 0.07 | C10: 0.07 | H10: =PREÇOS!C11 -> 3.3915 | I10: =IF(F10=0,,H10*(1+F10)*C10-(H10*B10)) -> 0 | J10: =IF(G10=0,IF(F10=0,,H10*(1+F10)*C10-(H10*B10)),H10*(1+G10)*C10-(H10*B10)) -> 0
A11: MA | B11: 0.07 | C11: 0.07 | H11: =PREÇOS!C12 -> 3.3915 | I11: =IF(F11=0,,H11*(1+F11)*C11-(H11*B11)) -> 0 | J11: =IF(G11=0,IF(F11=0,,H11*(1+F11)*C11-(H11*B11)),H11*(1+G11)*C11-(H11*B11)) -> 0
A12: MG | B12: 0.12 | C12: 0.18 | D12: 0.4 | F12: 0.5024 | H12: =PREÇOS!C13 -> 3.591 | I12: =IF(F12=0,,H12*(1+F12)*C12-(H12*B12)) -> 0.54020131 | J12: =IF(G12=0,IF(F12=0,,H12*(1+F12)*C12-(H12*B12)),H12*(1+G12)*C12-(H12*B12)) -> 0.54020131
A13: MS | B13: 0.07 | C13: 0.07 | H13: =PREÇOS!C14 -> 3.3915 | I13: =IF(F13=0,,H13*(1+F13)*C13-(H13*B13)) -> 0 | J13: =IF(G13=0,IF(F13=0,,H13*(1+F13)*C13-(H13*B13)),H13*(1+G13)*C13-(H13*B13)) -> 0
A14: MT | B14: 0.07 | C14: 0.17 | D14: 0.4552 | F14: 0.6305 | H14: =PREÇOS!C15 -> 3.3915 | I14: =IF(F14=0,,H14*(1+F14)*C14-(H14*B14)) -> 0.70266793 | J14: =IF(G14=0,IF(F14=0,,H14*(1+F14)*C14-(H14*B14)),H14*(1+G14)*C14-(H14*B14)) -> 0.70266793
A15: PA | B15: 0.07 | C15: 0.07 | H15: =PREÇOS!C16 -> 3.3915 | I15: =IF(F15=0,,H15*(1+F15)*C15-(H15*B15)) -> 0 | J15: =IF(G15=0,IF(F15=0,,H15*(1+F15)*C15-(H15*B15)),H15*(1+G15)*C15-(H15*B15)) -> 0
A16: PB | B16: 0.07 | C16: 0.07 | H16: =PREÇOS!C17 -> 3.3915 | I16: =IF(F16=0,,H16*(1+F16)*C16-(H16*B16)) -> 0 | J16: =IF(G16=0,IF(F16=0,,H16*(1+F16)*C16-(H16*B16)),H16*(1+G16)*C16-(H16*B16)) -> 0
A17: PE | B17: 0.07 | C17: 0.07 | H17: =PREÇOS!C18 -> 3.3915 | I17: =IF(F17=0,,H17*(1+F17)*C17-(H17*B17)) -> 0 | J17: =IF(G17=0,IF(F17=0,,H17*(1+F17)*C17-(H17*B17)),H17*(1+G17)*C17-(H17*B17)) -> 0
A18: PI | B18: 0.07 | C18: 0.07 | H18: =PREÇOS!C19 -> 3.3915 | I18: =IF(F18=0,,H18*(1+F18)*C18-(H18*B18)) -> 0 | J18: =IF(G18=0,IF(F18=0,,H18*(1+F18)*C18-(H18*B18)),H18*(1+G18)*C18-(H18*B18)) -> 0
A19: PR | B19: 0.12 | C19: 0.195 | D19: 0.5432 | E19: 0.163 | F19: 0.687 | G19: 0.1968 | H19: =PREÇOS!C20 -> 3.591 | I19: =IF(F19=0,,H19*(1+F19)*C19-(H19*B19)) -> 0.75039331 | J19: =IF(G19=0,IF(F19=0,,H19*(1+F19)*C19-(H19*B19)),H19*(1+G19)*C19-(H19*B19)) -> 0.40713322
A20: RJ | B20: 0.12 | C20: 0.22 | D20: 0.4698 | F20: 0.6582 | H20: =PREÇOS!C21 -> 3.591 | I20: =IF(F20=0,,H20*(1+F20)*C20-(H20*B20)) -> 0.87909116 | J20: =IF(G20=0,IF(F20=0,,H20*(1+F20)*C20-(H20*B20)),H20*(1+G20)*C20-(H20*B20)) -> 0.87909116
A21: RN | B21: 0.07 | C21: 0.07 | H21: =PREÇOS!C22 -> 3.3915 | I21: =IF(F21=0,,H21*(1+F21)*C21-(H21*B21)) -> 0 | J21: =IF(G21=0,IF(F21=0,,H21*(1+F21)*C21-(H21*B21)),H21*(1+G21)*C21-(H21*B21)) -> 0
A22: RO | B22: 0.07 | C22: 0.07 | H22: =PREÇOS!C23 -> 3.3915 | I22: =IF(F22=0,,H22*(1+F22)*C22-(H22*B22)) -> 0 | J22: =IF(G22=0,IF(F22=0,,H22*(1+F22)*C22-(H22*B22)),H22*(1+G22)*C22-(H22*B22)) -> 0
A23: RR | B23: 0.07 | C23: 0.07 | H23: =PREÇOS!C24 -> 3.3915 | I23: =IF(F23=0,,H23*(1+F23)*C23-(H23*B23)) -> 0 | J23: =IF(G23=0,IF(F23=0,,H23*(1+F23)*C23-(H23*B23)),H23*(1+G23)*C23-(H23*B23)) -> 0
A24: RS | B24: 0.12 | C24: 0.12 | H24: =PREÇOS!C25 -> 3.591 | I24: =IF(F24=0,,H24*(1+F24)*C24-(H24*B24)) -> 0 | J24: =IF(G24=0,IF(F24=0,,H24*(1+F24)*C24-(H24*B24)),H24*(1+G24)*C24-(H24*B24)) -> 0
A25: SC | B25: 0.12 | C25: 0.12 | H25: =PREÇOS!C26 -> 3.591 | I25: =IF(F25=0,,H25*(1+F25)*C25-(H25*B25)) -> 0 | J25: =IF(G25=0,IF(F25=0,,H25*(1+F25)*C25-(H25*B25)),H25*(1+G25)*C25-(H25*B25)) -> 0
A26: SE | B26: 0.07 | C26: 0.07 | H26: =PREÇOS!C27 -> 3.3915 | I26: =IF(F26=0,,H26*(1+F26)*C26-(H26*B26)) -> 0 | J26: =IF(G26=0,IF(F26=0,,H26*(1+F26)*C26-(H26*B26)),H26*(1+G26)*C26-(H26*B26)) -> 0
A27: SP | B27: 0.12 | C27: 0.18 | D27: 0.8807 | F27: 0.8807 | H27: =PREÇOS!C28 -> 3.591 | I27: =IF(F27=0,,H27*(1+F27)*C27-(H27*B27)) -> 0.78472687 | J27: =IF(G27=0,IF(F27=0,,H27*(1+F27)*C27-(H27*B27)),H27*(1+G27)*C27-(H27*B27)) -> 0.78472687
A28: SP/Atacado | B28: =B27 -> 0.12 | C28: =C27 -> 0.18 | D28: =D27 -> 0.8807 | E28: =E27 -> 0 | F28: =F27 -> 0.8807 | G28: =G27 -> 0 | H28: =PREÇOS!C29 -> 3.591 | I28: =IF(F28=0,,H28*(1+F28)*C28-(H28*B28)) -> 0.78472687 | J28: =IF(G28=0,IF(F28=0,,H28*(1+F28)*C28-(H28*B28)),H28*(1+G28)*C28-(H28*B28)) -> 0.78472687
A29: TO | B29: 0.07 | C29: 0.07 | H29: =PREÇOS!C30 -> 3.3915 | I29: =IF(F29=0,,H29*(1+F29)*C29-(H29*B29)) -> 0 | J29: =IF(G29=0,IF(F29=0,,H29*(1+F29)*C29-(H29*B29)),H29*(1+G29)*C29-(H29*B29)) -> 0
A30: EX | H30: =PREÇOS!C31 -> 0 | I30: =IF(F30=0,,H30*(1+F30)*C30-(H30*B30)) -> 0 | J30: =IF(G30=0,IF(F30=0,,H30*(1+F30)*C30-(H30*B30)),H30*(1+G30)*C30-(H30*B30)) -> 0

Sheet ST BISCOTTI
A1: Estado | B1: Aliquota interestadual | C1: Aliquota interna | D1: MVA (normal) | E1: MVA (simples) | F1: Ajustada (normal) | G1: Ajustada (simples) | H1: Preço | I1: ST Normal | J1: ST Simples
A2: AC | B2: 0.07 | C2: =VLOOKUP(A2,[1]DIFAL!$C$13:$H$39,6,) -> 0.19 | H2: =PREÇOS!H3 -> 7.5335 | I2: =IF(F2=0,,H2*(1+F2)*C2-(H2*B2)) -> 0 | J2: =IF(G2=0,IF(F2=0,,H2*(1+F2)*C2-(H2*B2)),H2*(1+G2)*C2-(H2*B2)) -> 0
A3: AL | B3: 0.07 | C3: 0.2 | F3: 0.5113 | H3: =PREÇOS!H4 -> 7.5335 | I3: =IF(F3=0,,H3*(1+F3)*C3-(H3*B3)) -> 1.7497307 | J3: =IF(G3=0,IF(F3=0,,H3*(1+F3)*C3-(H3*B3)),H3*(1+G3)*C3-(H3*B3)) -> 1.7497307
A4: AM | B4: 0.07 | C4: =VLOOKUP(A4,[1]DIFAL!$C$13:$H$39,6,) -> 0.2 | H4: =PREÇOS!H5 -> 7.5335 | I4: =IF(F4=0,,H4*(1+F4)*C4-(H4*B4)) -> 0 | J4: =IF(G4=0,IF(F4=0,,H4*(1+F4)*C4-(H4*B4)),H4*(1+G4)*C4-(H4*B4)) -> 0
A5: AP | B5: 0.07 | C5: =VLOOKUP(A5,[1]DIFAL!$C$13:$H$39,5,) -> 0.18 | F5: 0.5198 | H5: =PREÇOS!H6 -> 7.5335 | I5: =IF(F5=0,,H5*(1+F5)*C5-(H5*B5)) -> 1.5335494 | J5: =IF(G5=0,IF(F5=0,,H5*(1+F5)*C5-(H5*B5)),H5*(1+G5)*C5-(H5*B5)) -> 1.5335494
A6: BA | B6: 0.07 | C6: =VLOOKUP(A6,[1]DIFAL!$C$13:$H$39,6,) -> 0.19 | H6: =PREÇOS!H7 -> 7.5335 | I6: =IF(F6=0,,H6*(1+F6)*C6-(H6*B6)) -> 0 | J6: =IF(G6=0,IF(F6=0,,H6*(1+F6)*C6-(H6*B6)),H6*(1+G6)*C6-(H6*B6)) -> 0
A7: CE | B7: 0.07 | C7: =VLOOKUP(A7,[1]DIFAL!$C$13:$H$39,6,) -> 0.2 | H7: =PREÇOS!H8 -> 7.5335 | I7: =IF(F7=0,,H7*(1+F7)*C7-(H7*B7)) -> 0 | J7: =IF(G7=0,IF(F7=0,,H7*(1+F7)*C7-(H7*B7)),H7*(1+G7)*C7-(H7*B7)) -> 0
A8: DF | B8: 0.07 | C8: =VLOOKUP(A8,[1]DIFAL!$C$13:$H$39,5,) -> 0.18 | H8: =PREÇOS!H9 -> 7.5335 | I8: =IF(F8=0,,H8*(1+F8)*C8-(H8*B8)) -> 0 | J8: =IF(G8=0,IF(F8=0,,H8*(1+F8)*C8-(H8*B8)),H8*(1+G8)*C8-(H8*B8)) -> 0
A9: ES | B9: 0.07 | C9: =VLOOKUP(A9,[1]DIFAL!$C$13:$H$39,5,) -> 0.17 | H9: =PREÇOS!H10 -> 7.5335 | I9: =IF(F9=0,,H9*(1+F9)*C9-(H9*B9)) -> 0 | J9: =IF(G9=0,IF(F9=0,,H9*(1+F9)*C9-(H9*B9)),H9*(1+G9)*C9-(H9*B9)) -> 0
A10: GO | B10: 0.07 | C10: =VLOOKUP(A10,[1]DIFAL!$C$13:$H$39,5,) -> 0.17 | H10: =PREÇOS!H11 -> 7.5335 | I10: =IF(F10=0,,H10*(1+F10)*C10-(H10*B10)) -> 0 | J10: =IF(G10=0,IF(F10=0,,H10*(1+F10)*C10-(H10*B10)),H10*(1+G10)*C10-(H10*B10)) -> 0
A11: MA | B11: 0.07 | C11: =VLOOKUP(A11,[1]DIFAL!$C$13:$H$39,6,) -> 0.2 | H11: =PREÇOS!H12 -> 7.5335 | I11: =IF(F11=0,,H11*(1+F11)*C11-(H11*B11)) -> 0 | J11: =IF(G11=0,IF(F11=0,,H11*(1+F11)*C11-(H11*B11)),H11*(1+G11)*C11-(H11*B11)) -> 0
A12: MG | B12: 0.12 | C12: 0.12 | F12: 0.25 | H12: =PREÇOS!H13 -> 7.98 | I12: =IF(F12=0,,H12*(1+F12)*C12-(H12*B12)) -> 0.2394 | J12: =IF(G12=0,IF(F12=0,,H12*(1+F12)*C12-(H12*B12)),H12*(1+G12)*C12-(H12*B12)) -> 0.2394
A13: MS | B13: 0.07 | C13: =VLOOKUP(A13,[1]DIFAL!$C$13:$H$39,5,) -> 0.17 | H13: =PREÇOS!H14 -> 7.5335 | I13: =IF(F13=0,,H13*(1+F13)*C13-(H13*B13)) -> 0 | J13: =IF(G13=0,IF(F13=0,,H13*(1+F13)*C13-(H13*B13)),H13*(1+G13)*C13-(H13*B13)) -> 0
A14: MT | B14: 0.07 | C14: =VLOOKUP(A14,[1]DIFAL!$C$13:$H$39,5,) -> 0.17 | F14: 0.3978 | H14: =PREÇOS!H15 -> 7.5335 | I14: =IF(F14=0,,H14*(1+F14)*C14-(H14*B14)) -> 1.2628105 | J14: =IF(G14=0,IF(F14=0,,H14*(1+F14)*C14-(H14*B14)),H14*(1+G14)*C14-(H14*B14)) -> 1.2628105
A15: PA | B15: 0.07 | C15: =VLOOKUP(A15,[1]DIFAL!$C$13:$H$39,6,) -> 0.19 | H15: =PREÇOS!H16 -> 7.5335 | I15: =IF(F15=0,,H15*(1+F15)*C15-(H15*B15)) -> 0 | J15: =IF(G15=0,IF(F15=0,,H15*(1+F15)*C15-(H15*B15)),H15*(1+G15)*C15-(H15*B15)) -> 0
A16: PB | B16: 0.07 | C16: =VLOOKUP(A16,[1]DIFAL!$C$13:$H$39,5,) -> 0.18 | H16: =PREÇOS!H17 -> 7.5335 | I16: =IF(F16=0,,H16*(1+F16)*C16-(H16*B16)) -> 0 | J16: =IF(G16=0,IF(F16=0,,H16*(1+F16)*C16-(H16*B16)),H16*(1+G16)*C16-(H16*B16)) -> 0
A17: PE | B17: 0.07 | C17: =VLOOKUP(A17,[1]DIFAL!$C$13:$H$39,5,) -> 0.18 | H17: =PREÇOS!H18 -> 7.5335 | I17: =IF(F17=0,,H17*(1+F17)*C17-(H17*B17)) -> 0 | J17: =IF(G17=0,IF(F17=0,,H17*(1+F17)*C17-(H17*B17)),H17*(1+G17)*C17-(H17*B17)) -> 0
A18: PI | B18: 0.07 | C18: =VLOOKUP(A18,[1]DIFAL!$C$13:$H$39,6,) -> 0.21 | H18: =PREÇOS!H19 -> 7.5335 | I18: =IF(F18=0,,H18*(1+F18)*C18-(H18*B18)) -> 0 | J18: =IF(G18=0,IF(F18=0,,H18*(1+F18)*C18-(H18*B18)),H18*(1+G18)*C18-(H18*B18)) -> 0
A19: PR | B19: 0.12 | C19: 0.12 | H19: =PREÇOS!H20 -> 7.98 | I19: =IF(F19=0,,H19*(1+F19)*C19-(H19*B19)) -> 0 | J19: =IF(G19=0,IF(F19=0,,H19*(1+F19)*C19-(H19*B19)),H19*(1+G19)*C19-(H19*B19)) -> 0
A20: RJ | B20: 0.12 | C20: 0.22 | F20: 0.5253 | H20: =PREÇOS!H21 -> 7.98 | I20: =IF(F20=0,,H20*(1+F20)*C20-(H20*B20)) -> 1.7202167 | J20: =IF(G20=0,IF(F20=0,,H20*(1+F20)*C20-(H20*B20)),H20*(1+G20)*C20-(H20*B20)) -> 1.7202167
A21: RN | B21: 0.07 | C21: =VLOOKUP(A21,[1]DIFAL!$C$13:$H$39,6,) -> 0.2 | H21: =PREÇOS!H22 -> 7.5335 | I21: =IF(F21=0,,H21*(1+F21)*C21-(H21*B21)) -> 0 | J21: =IF(G21=0,IF(F21=0,,H21*(1+F21)*C21-(H21*B21)),H21*(1+G21)*C21-(H21*B21)) -> 0
A22: RO | B22: 0.07 | C22: =VLOOKUP(A22,[1]DIFAL!$C$13:$H$39,5,) -> 0.175 | H22: =PREÇOS!H23 -> 7.5335 | I22: =IF(F22=0,,H22*(1+F22)*C22-(H22*B22)) -> 0 | J22: =IF(G22=0,IF(F22=0,,H22*(1+F22)*C22-(H22*B22)),H22*(1+G22)*C22-(H22*B22)) -> 0
A23: RR | B23: 0.07 | C23: =VLOOKUP(A23,[1]DIFAL!$C$13:$H$39,6,) -> 0.2 | H23: =PREÇOS!H24 -> 7.5335 | I23: =IF(F23=0,,H23*(1+F23)*C23-(H23*B23)) -> 0 | J23: =IF(G23=0,IF(F23=0,,H23*(1+F23)*C23-(H23*B23)),H23*(1+G23)*C23-(H23*B23)) -> 0
A24: RS | B24: 0.12 | C24: =VLOOKUP(A24,[1]DIFAL!$C$13:$H$39,5,) -> 0.17 | H24: =PREÇOS!H25 -> 7.98 | I24: =IF(F24=0,,H24*(1+F24)*C24-(H24*B24)) -> 0 | J24: =IF(G24=0,IF(F24=0,,H24*(1+F24)*C24-(H24*B24)),H24*(1+G24)*C24-(H24*B24)) -> 0
A25: SC | B25: 0.12 | C25: =VLOOKUP(A25,[1]DIFAL!$C$13:$H$39,5,) -> 0.17 | H25: =PREÇOS!H26 -> 7.98 | I25: =IF(F25=0,,H25*(1+F25)*C25-(H25*B25)) -> 0 | J25: =IF(G25=0,IF(F25=0,,H25*(1+F25)*C25-(H25*B25)),H25*(1+G25)*C25-(H25*B25)) -> 0
A26: SE | B26: 0.07 | C26: 0.2 | H26: =PREÇOS!H27 -> 7.5335 | I26: =IF(F26=0,,H26*(1+F26)*C26-(H26*B26)) -> 0 | J26: =IF(G26=0,IF(F26=0,,H26*(1+F26)*C26-(H26*B26)),H26*(1+G26)*C26-(H26*B26)) -> 0
A27: SP | B27: 0.12 | C27: =VLOOKUP(A27,[1]DIFAL!$C$13:$H$39,5,) -> 0.18 | D27: 0.5917 | F27: 0.5917 | H27: =PREÇOS!H28 -> 7.98 | I27: =IF(F27=0,,H27*(1+F27)*C27-(H27*B27)) -> 1.3287179 | J27: =IF(G27=0,IF(F27=0,,H27*(1+F27)*C27-(H27*B27)),H27*(1+G27)*C27-(H27*B27)) -> 1.3287179
A28: SP/Atacado | B28: =B27 -> 0.12 | C28: =C27 -> 0.18 | D28: 0.4832 | E28: =E27 -> 0 | F28: 0.4832 | G28: =G27 -> 0 | H28: =PREÇOS!H29 -> 7.98 | I28: =IF(F28=0,,H28*(1+F28)*C28-(H28*B28)) -> 1.1728685 | J28: =IF(G28=0,IF(F28=0,,H28*(1+F28)*C28-(H28*B28)),H28*(1+G28)*C28-(H28*B28)) -> 1.1728685
A29: TO | B29: 0.07 | C29: =VLOOKUP(A29,[1]DIFAL!$C$13:$H$39,6,) -> 0.2 | H29: =PREÇOS!H30 -> 7.5335 | I29: =IF(F29=0,,H29*(1+F29)*C29-(H29*B29)) -> 0 | J29: =IF(G29=0,IF(F29=0,,H29*(1+F29)*C29-(H29*B29)),H29*(1+G29)*C29-(H29*B29)) -> 0
A30: EX

Sheet ST CEREAL
A1: Estado | B1: Aliquota interestadual | C1: Aliquota interna | D1: MVA (normal) | E1: MVA (simples) | F1: Ajustada (normal) | G1: Ajustada (simples) | H1: Preço | I1: ST Normal | J1: ST Simples
A2: AC | B2: =VLOOKUP(A2,[1]DIFAL!$C$13:$E$39,3,0) -> 0.07 | C2: 0.17 | H2: =PREÇOS!G3 -> 7.4575 | I2: =IF(F2=0,,H2*(1+F2)*C2-(H2*B2)) -> 0 | J2: =IF(G2=0,IF(F2=0,,H2*(1+F2)*C2-(H2*B2)),H2*(1+G2)*C2-(H2*B2)) -> 0
A3: AL | B3: =VLOOKUP(A3,[1]DIFAL!$C$13:$E$39,3,0) -> 0.07 | C3: 0.2 | F3: 0.71 | H3: =PREÇOS!G4 -> 7.4575 | I3: =IF(F3=0,,H3*(1+F3)*C3-(H3*B3)) -> 2.02844 | J3: =IF(G3=0,IF(F3=0,,H3*(1+F3)*C3-(H3*B3)),H3*(1+G3)*C3-(H3*B3)) -> 2.02844
A4: AM | B4: =VLOOKUP(A4,[1]DIFAL!$C$13:$E$39,3,0) -> 0.07 | C4: 0.2 | F4: 0.5538 | H4: =PREÇOS!G5 -> 7.4575 | I4: =IF(F4=0,,H4*(1+F4)*C4-(H4*B4)) -> 1.7954677 | J4: =IF(G4=0,IF(F4=0,,H4*(1+F4)*C4-(H4*B4)),H4*(1+G4)*C4-(H4*B4)) -> 1.7954677
A5: AP | B5: =VLOOKUP(A5,[1]DIFAL!$C$13:$E$39,3,0) -> 0.07 | C5: 0.18 | H5: =PREÇOS!G6 -> 7.4575 | I5: =IF(F5=0,,H5*(1+F5)*C5-(H5*B5)) -> 0 | J5: =IF(G5=0,IF(F5=0,,H5*(1+F5)*C5-(H5*B5)),H5*(1+G5)*C5-(H5*B5)) -> 0
A6: BA | B6: =VLOOKUP(A6,[1]DIFAL!$C$13:$E$39,3,0) -> 0.07 | C6: 0.19 | H6: =PREÇOS!G7 -> 7.4575 | I6: =IF(F6=0,,H6*(1+F6)*C6-(H6*B6)) -> 0 | J6: =IF(G6=0,IF(F6=0,,H6*(1+F6)*C6-(H6*B6)),H6*(1+G6)*C6-(H6*B6)) -> 0
A7: CE | B7: =VLOOKUP(A7,[1]DIFAL!$C$13:$E$39,3,0) -> 0.07 | C7: 0.2 | H7: =PREÇOS!G8 -> 7.4575 | I7: =IF(F7=0,,H7*(1+F7)*C7-(H7*B7)) -> 0 | J7: =IF(G7=0,IF(F7=0,,H7*(1+F7)*C7-(H7*B7)),H7*(1+G7)*C7-(H7*B7)) -> 0
A8: DF | B8: =VLOOKUP(A8,[1]DIFAL!$C$13:$E$39,3,0) -> 0.07 | C8: 0.18 | H8: =PREÇOS!G9 -> 7.4575 | I8: =IF(F8=0,,H8*(1+F8)*C8-(H8*B8)) -> 0 | J8: =IF(G8=0,IF(F8=0,,H8*(1+F8)*C8-(H8*B8)),H8*(1+G8)*C8-(H8*B8)) -> 0
A9: ES | B9: =VLOOKUP(A9,[1]DIFAL!$C$13:$E$39,3,0) -> 0.07 | C9: 0.17 | H9: =PREÇOS!G10 -> 7.4575 | I9: =IF(F9=0,,H9*(1+F9)*C9-(H9*B9)) -> 0 | J9: =IF(G9=0,IF(F9=0,,H9*(1+F9)*C9-(H9*B9)),H9*(1+G9)*C9-(H9*B9)) -> 0
A10: GO | B10: =VLOOKUP(A10,[1]DIFAL!$C$13:$E$39,3,0) -> 0.07 | C10: 0.17 | H10: =PREÇOS!G11 -> 7.4575 | I10: =IF(F10=0,,H10*(1+F10)*C10-(H10*B10)) -> 0 | J10: =IF(G10=0,IF(F10=0,,H10*(1+F10)*C10-(H10*B10)),H10*(1+G10)*C10-(H10*B10)) -> 0
A11: MA | B11: =VLOOKUP(A11,[1]DIFAL!$C$13:$E$39,3,0) -> 0.07 | C11: 0.2 | H11: =PREÇOS!G12 -> 7.4575 | I11: =IF(F11=0,,H11*(1+F11)*C11-(H11*B11)) -> 0 | J11: =IF(G11=0,IF(F11=0,,H11*(1+F11)*C11-(H11*B11)),H11*(1+G11)*C11-(H11*B11)) -> 0
A12: MG | B12: =VLOOKUP(A12,[1]DIFAL!$C$13:$E$39,3,0) -> 0.12 | C12: 0.18 | F12: 0.4488 | H12: =PREÇOS!G13 -> 7.885 | I12: =IF(F12=0,,H12*(1+F12)*C12-(H12*B12)) -> 1.1100818 | J12: =IF(G12=0,IF(F12=0,,H12*(1+F12)*C12-(H12*B12)),H12*(1+G12)*C12-(H12*B12)) -> 1.1100818
A13: MS | B13: =VLOOKUP(A13,[1]DIFAL!$C$13:$E$39,3,0) -> 0.07 | C13: 0.17 | H13: =PREÇOS!G14 -> 7.4575 | I13: =IF(F13=0,,H13*(1+F13)*C13-(H13*B13)) -> 0 | J13: =IF(G13=0,IF(F13=0,,H13*(1+F13)*C13-(H13*B13)),H13*(1+G13)*C13-(H13*B13)) -> 0
A14: MT | B14: =VLOOKUP(A14,[1]DIFAL!$C$13:$E$39,3,0) -> 0.07 | C14: 0.17 | F14: 0.4552 | H14: =PREÇOS!G15 -> 7.4575 | I14: =IF(F14=0,,H14*(1+F14)*C14-(H14*B14)) -> 1.3228412 | J14: =IF(G14=0,IF(F14=0,,H14*(1+F14)*C14-(H14*B14)),H14*(1+G14)*C14-(H14*B14)) -> 1.3228412
A15: PA | B15: =VLOOKUP(A15,[1]DIFAL!$C$13:$E$39,3,0) -> 0.07 | C15: 0.19 | H15: =PREÇOS!G16 -> 7.4575 | I15: =IF(F15=0,,H15*(1+F15)*C15-(H15*B15)) -> 0 | J15: =IF(G15=0,IF(F15=0,,H15*(1+F15)*C15-(H15*B15)),H15*(1+G15)*C15-(H15*B15)) -> 0
A16: PB | B16: =VLOOKUP(A16,[1]DIFAL!$C$13:$E$39,3,0) -> 0.07 | C16: 0.18 | H16: =PREÇOS!G17 -> 7.4575 | I16: =IF(F16=0,,H16*(1+F16)*C16-(H16*B16)) -> 0 | J16: =IF(G16=0,IF(F16=0,,H16*(1+F16)*C16-(H16*B16)),H16*(1+G16)*C16-(H16*B16)) -> 0
A17: PE | B17: =VLOOKUP(A17,[1]DIFAL!$C$13:$E$39,3,0) -> 0.07 | C17: 0.18 | H17: =PREÇOS!G18 -> 7.4575 | I17: =IF(F17=0,,H17*(1+F17)*C17-(H17*B17)) -> 0 | J17: =IF(G17=0,IF(F17=0,,H17*(1+F17)*C17-(H17*B17)),H17*(1+G17)*C17-(H17*B17)) -> 0
A18: PI | B18: =VLOOKUP(A18,[1]DIFAL!$C$13:$E$39,3,0) -> 0.07 | C18: 0.21 | H18: =PREÇOS!G19 -> 7.4575 | I18: =IF(F18=0,,H18*(1+F18)*C18-(H18*B18)) -> 0 | J18: =IF(G18=0,IF(F18=0,,H18*(1+F18)*C18-(H18*B18)),H18*(1+G18)*C18-(H18*B18)) -> 0
A19: PR | B19: 0.12 | C19: 0.195 | F19: 0.608 | H19: =PREÇOS!G20 -> 7.885 | I19: =IF(F19=0,,H19*(1+F19)*C19-(H19*B19)) -> 1.5262206 | J19: =IF(G19=0,IF(F19=0,,H19*(1+F19)*C19-(H19*B19)),H19*(1+G19)*C19-(H19*B19)) -> 1.5262206
A20: RJ | B20: =VLOOKUP(A20,[1]DIFAL!$C$13:$E$39,3,0) -> 0.12 | C20: 0.22 | F20: 0.5473 | H20: =PREÇOS!G21 -> 7.885 | I20: =IF(F20=0,,H20*(1+F20)*C20-(H20*B20)) -> 1.7379013 | J20: =IF(G20=0,IF(F20=0,,H20*(1+F20)*C20-(H20*B20)),H20*(1+G20)*C20-(H20*B20)) -> 1.7379013
A21: RN | B21: =VLOOKUP(A21,[1]DIFAL!$C$13:$E$39,3,0) -> 0.07 | C21: 0.2 | H21: =PREÇOS!G22 -> 7.4575 | I21: =IF(F21=0,,H21*(1+F21)*C21-(H21*B21)) -> 0 | J21: =IF(G21=0,IF(F21=0,,H21*(1+F21)*C21-(H21*B21)),H21*(1+G21)*C21-(H21*B21)) -> 0
A22: RO | B22: =VLOOKUP(A22,[1]DIFAL!$C$13:$E$39,3,0) -> 0.07 | C22: 0.175 | H22: =PREÇOS!G23 -> 7.4575 | I22: =IF(F22=0,,H22*(1+F22)*C22-(H22*B22)) -> 0 | J22: =IF(G22=0,IF(F22=0,,H22*(1+F22)*C22-(H22*B22)),H22*(1+G22)*C22-(H22*B22)) -> 0
A23: RR | B23: =VLOOKUP(A23,[1]DIFAL!$C$13:$E$39,3,0) -> 0.07 | C23: 0.2 | H23: =PREÇOS!G24 -> 7.4575 | I23: =IF(F23=0,,H23*(1+F23)*C23-(H23*B23)) -> 0 | J23: =IF(G23=0,IF(F23=0,,H23*(1+F23)*C23-(H23*B23)),H23*(1+G23)*C23-(H23*B23)) -> 0
A24: RS | B24: =VLOOKUP(A24,[1]DIFAL!$C$13:$E$39,3,0) -> 0.12 | C24: 0.17 | H24: =PREÇOS!G25 -> 7.885 | I24: =IF(F24=0,,H24*(1+F24)*C24-(H24*B24)) -> 0 | J24: =IF(G24=0,IF(F24=0,,H24*(1+F24)*C24-(H24*B24)),H24*(1+G24)*C24-(H24*B24)) -> 0
A25: SC | B25: =VLOOKUP(A25,[1]DIFAL!$C$13:$E$39,3,0) -> 0.12 | C25: 0.17 | H25: =PREÇOS!G26 -> 7.885 | I25: =IF(F25=0,,H25*(1+F25)*C25-(H25*B25)) -> 0 | J25: =IF(G25=0,IF(F25=0,,H25*(1+F25)*C25-(H25*B25)),H25*(1+G25)*C25-(H25*B25)) -> 0
A26: SE | B26: =VLOOKUP(A26,[1]DIFAL!$C$13:$E$39,3,0) -> 0.07 | C26: 0.2 | H26: =PREÇOS!G27 -> 7.4575 | I26: =IF(F26=0,,H26*(1+F26)*C26-(H26*B26)) -> 0 | J26: =IF(G26=0,IF(F26=0,,H26*(1+F26)*C26-(H26*B26)),H26*(1+G26)*C26-(H26*B26)) -> 0
A27: SP | B27: =VLOOKUP(A27,[1]DIFAL!$C$13:$E$39,3,0) -> 0.12 | C27: 0.18 | F27: 0.463 | H27: =PREÇOS!G28 -> 7.885 | I27: =IF(F27=0,,H27*(1+F27)*C27-(H27*B27)) -> 1.1302359 | J27: =IF(G27=0,IF(F27=0,,H27*(1+F27)*C27-(H27*B27)),H27*(1+G27)*C27-(H27*B27)) -> 1.1302359
A28: SP/Atacado | B28: =B27 -> 0.12 | C28: =C27 -> 0.18 | D28: =D27 -> 0 | E28: =E27 -> 0 | F28: =F27 -> 0.463 | G28: =G27 -> 0 | H28: =PREÇOS!G29 -> 7.885 | I28: =IF(F28=0,,H28*(1+F28)*C28-(H28*B28)) -> 1.1302359 | J28: =IF(G28=0,IF(F28=0,,H28*(1+F28)*C28-(H28*B28)),H28*(1+G28)*C28-(H28*B28)) -> 1.1302359
A29: TO | B29: =VLOOKUP(A29,[1]DIFAL!$C$13:$E$39,3,0) -> 0.07 | C29: 0.2 | H29: =PREÇOS!G30 -> 7.4575 | I29: =IF(F29=0,,H29*(1+F29)*C29-(H29*B29)) -> 0 | J29: =IF(G29=0,IF(F29=0,,H29*(1+F29)*C29-(H29*B29)),H29*(1+G29)*C29-(H29*B29)) -> 0
A30: EX | H30: =PREÇOS!G31 -> 0 | I30: =IF(F30=0,,H30*(1+F30)*C30-(H30*B30)) -> 0 | J30: =IF(G30=0,IF(F30=0,,H30*(1+F30)*C30-(H30*B30)),H30*(1+G30)*C30-(H30*B30)) -> 0

Sheet ST CEREAL SABOR POUCH 170
A1: Estado | B1: Aliquota interestadual | C1: Aliquota interna | D1: MVA (normal) | E1: MVA (simples) | F1: Ajustada (normal) | G1: Ajustada (simples) | H1: Preço | I1: ST Normal | J1: ST Simples
A2: AC | B2: =VLOOKUP(A2,[1]DIFAL!$C$13:$E$39,3,0) -> 0.07 | C2: 0.17 | H2: =PREÇOS!J3 -> 6.0325 | I2: =IF(F2=0,,H2*(1+F2)*C2-(H2*B2)) -> 0 | J2: =IF(G2=0,IF(F2=0,,H2*(1+F2)*C2-(H2*B2)),H2*(1+G2)*C2-(H2*B2)) -> 0
A3: AL | B3: =VLOOKUP(A3,[1]DIFAL!$C$13:$E$39,3,0) -> 0.07 | C3: 0.2 | F3: 0.71 | H3: =PREÇOS!J4 -> 6.0325 | I3: =IF(F3=0,,H3*(1+F3)*C3-(H3*B3)) -> 1.64084 | J3: =IF(G3=0,IF(F3=0,,H3*(1+F3)*C3-(H3*B3)),H3*(1+G3)*C3-(H3*B3)) -> 1.64084
A4: AM | B4: =VLOOKUP(A4,[1]DIFAL!$C$13:$E$39,3,0) -> 0.07 | C4: 0.2 | F4: 0.5538 | H4: =PREÇOS!J5 -> 6.0325 | I4: =IF(F4=0,,H4*(1+F4)*C4-(H4*B4)) -> 1.4523847 | J4: =IF(G4=0,IF(F4=0,,H4*(1+F4)*C4-(H4*B4)),H4*(1+G4)*C4-(H4*B4)) -> 1.4523847
A5: AP | B5: =VLOOKUP(A5,[1]DIFAL!$C$13:$E$39,3,0) -> 0.07 | C5: 0.18 | H5: =PREÇOS!J6 -> 6.0325 | I5: =IF(F5=0,,H5*(1+F5)*C5-(H5*B5)) -> 0 | J5: =IF(G5=0,IF(F5=0,,H5*(1+F5)*C5-(H5*B5)),H5*(1+G5)*C5-(H5*B5)) -> 0
A6: BA | B6: =VLOOKUP(A6,[1]DIFAL!$C$13:$E$39,3,0) -> 0.07 | C6: 0.19 | H6: =PREÇOS!J7 -> 6.0325 | I6: =IF(F6=0,,H6*(1+F6)*C6-(H6*B6)) -> 0 | J6: =IF(G6=0,IF(F6=0,,H6*(1+F6)*C6-(H6*B6)),H6*(1+G6)*C6-(H6*B6)) -> 0
A7: CE | B7: =VLOOKUP(A7,[1]DIFAL!$C$13:$E$39,3,0) -> 0.07 | C7: 0.2 | H7: =PREÇOS!J8 -> 6.0325 | I7: =IF(F7=0,,H7*(1+F7)*C7-(H7*B7)) -> 0 | J7: =IF(G7=0,IF(F7=0,,H7*(1+F7)*C7-(H7*B7)),H7*(1+G7)*C7-(H7*B7)) -> 0
A8: DF | B8: =VLOOKUP(A8,[1]DIFAL!$C$13:$E$39,3,0) -> 0.07 | C8: 0.18 | H8: =PREÇOS!J9 -> 6.0325 | I8: =IF(F8=0,,H8*(1+F8)*C8-(H8*B8)) -> 0 | J8: =IF(G8=0,IF(F8=0,,H8*(1+F8)*C8-(H8*B8)),H8*(1+G8)*C8-(H8*B8)) -> 0
A9: ES | B9: =VLOOKUP(A9,[1]DIFAL!$C$13:$E$39,3,0) -> 0.07 | C9: 0.17 | H9: =PREÇOS!J10 -> 5.529 | I9: =IF(F9=0,,H9*(1+F9)*C9-(H9*B9)) -> 0 | J9: =IF(G9=0,IF(F9=0,,H9*(1+F9)*C9-(H9*B9)),H9*(1+G9)*C9-(H9*B9)) -> 0
A10: GO | B10: =VLOOKUP(A10,[1]DIFAL!$C$13:$E$39,3,0) -> 0.07 | C10: 0.17 | H10: =PREÇOS!J11 -> 6.0325 | I10: =IF(F10=0,,H10*(1+F10)*C10-(H10*B10)) -> 0 | J10: =IF(G10=0,IF(F10=0,,H10*(1+F10)*C10-(H10*B10)),H10*(1+G10)*C10-(H10*B10)) -> 0
A11: MA | B11: =VLOOKUP(A11,[1]DIFAL!$C$13:$E$39,3,0) -> 0.07 | C11: 0.2 | H11: =PREÇOS!J12 -> 6.0325 | I11: =IF(F11=0,,H11*(1+F11)*C11-(H11*B11)) -> 0 | J11: =IF(G11=0,IF(F11=0,,H11*(1+F11)*C11-(H11*B11)),H11*(1+G11)*C11-(H11*B11)) -> 0
A12: MG | B12: =VLOOKUP(A12,[1]DIFAL!$C$13:$E$39,3,0) -> 0.12 | C12: 0.18 | F12: 0.4488 | H12: =PREÇOS!J13 -> 5.8425 | I12: =IF(F12=0,,H12*(1+F12)*C12-(H12*B12)) -> 0.82253052 | J12: =IF(G12=0,IF(F12=0,,H12*(1+F12)*C12-(H12*B12)),H12*(1+G12)*C12-(H12*B12)) -> 0.82253052
A13: MS | B13: =VLOOKUP(A13,[1]DIFAL!$C$13:$E$39,3,0) -> 0.07 | C13: 0.17 | H13: =PREÇOS!J14 -> 6.0325 | I13: =IF(F13=0,,H13*(1+F13)*C13-(H13*B13)) -> 0 | J13: =IF(G13=0,IF(F13=0,,H13*(1+F13)*C13-(H13*B13)),H13*(1+G13)*C13-(H13*B13)) -> 0
A14: MT | B14: =VLOOKUP(A14,[1]DIFAL!$C$13:$E$39,3,0) -> 0.07 | C14: 0.17 | F14: 0.4552 | H14: =PREÇOS!J15 -> 6.0325 | I14: =IF(F14=0,,H14*(1+F14)*C14-(H14*B14)) -> 1.070069 | J14: =IF(G14=0,IF(F14=0,,H14*(1+F14)*C14-(H14*B14)),H14*(1+G14)*C14-(H14*B14)) -> 1.070069
A15: PA | B15: =VLOOKUP(A15,[1]DIFAL!$C$13:$E$39,3,0) -> 0.07 | C15: 0.19 | H15: =PREÇOS!J16 -> 6.0325 | I15: =IF(F15=0,,H15*(1+F15)*C15-(H15*B15)) -> 0 | J15: =IF(G15=0,IF(F15=0,,H15*(1+F15)*C15-(H15*B15)),H15*(1+G15)*C15-(H15*B15)) -> 0
A16: PB | B16: =VLOOKUP(A16,[1]DIFAL!$C$13:$E$39,3,0) -> 0.07 | C16: 0.18 | H16: =PREÇOS!J17 -> 6.0325 | I16: =IF(F16=0,,H16*(1+F16)*C16-(H16*B16)) -> 0 | J16: =IF(G16=0,IF(F16=0,,H16*(1+F16)*C16-(H16*B16)),H16*(1+G16)*C16-(H16*B16)) -> 0
A17: PE | B17: =VLOOKUP(A17,[1]DIFAL!$C$13:$E$39,3,0) -> 0.07 | C17: 0.18 | H17: =PREÇOS!J18 -> 6.0325 | I17: =IF(F17=0,,H17*(1+F17)*C17-(H17*B17)) -> 0 | J17: =IF(G17=0,IF(F17=0,,H17*(1+F17)*C17-(H17*B17)),H17*(1+G17)*C17-(H17*B17)) -> 0
A18: PI | B18: =VLOOKUP(A18,[1]DIFAL!$C$13:$E$39,3,0) -> 0.07 | C18: 0.21 | H18: =PREÇOS!J19 -> 6.0325 | I18: =IF(F18=0,,H18*(1+F18)*C18-(H18*B18)) -> 0 | J18: =IF(G18=0,IF(F18=0,,H18*(1+F18)*C18-(H18*B18)),H18*(1+G18)*C18-(H18*B18)) -> 0
A19: PR | B19: 0.12 | C19: 0.195 | F19: 0.608 | H19: =PREÇOS!J20 -> 5.8425 | I19: =IF(F19=0,,H19*(1+F19)*C19-(H19*B19)) -> 1.1308743 | J19: =IF(G19=0,IF(F19=0,,H19*(1+F19)*C19-(H19*B19)),H19*(1+G19)*C19-(H19*B19)) -> 1.1308743
A20: RJ | B20: =VLOOKUP(A20,[1]DIFAL!$C$13:$E$39,3,0) -> 0.12 | C20: 0.22 | F20: 0.5473 | H20: =PREÇOS!J21 -> 5.8425 | I20: =IF(F20=0,,H20*(1+F20)*C20-(H20*B20)) -> 1.2877221 | J20: =IF(G20=0,IF(F20=0,,H20*(1+F20)*C20-(H20*B20)),H20*(1+G20)*C20-(H20*B20)) -> 1.2877221
A21: RN | B21: =VLOOKUP(A21,[1]DIFAL!$C$13:$E$39,3,0) -> 0.07 | C21: 0.2 | H21: =PREÇOS!J22 -> 6.0325 | I21: =IF(F21=0,,H21*(1+F21)*C21-(H21*B21)) -> 0 | J21: =IF(G21=0,IF(F21=0,,H21*(1+F21)*C21-(H21*B21)),H21*(1+G21)*C21-(H21*B21)) -> 0
A22: RO | B22: =VLOOKUP(A22,[1]DIFAL!$C$13:$E$39,3,0) -> 0.07 | C22: 0.175 | H22: =PREÇOS!J23 -> 6.0325 | I22: =IF(F22=0,,H22*(1+F22)*C22-(H22*B22)) -> 0 | J22: =IF(G22=0,IF(F22=0,,H22*(1+F22)*C22-(H22*B22)),H22*(1+G22)*C22-(H22*B22)) -> 0
A23: RR | B23: =VLOOKUP(A23,[1]DIFAL!$C$13:$E$39,3,0) -> 0.07 | C23: 0.2 | H23: =PREÇOS!J24 -> 6.0325 | I23: =IF(F23=0,,H23*(1+F23)*C23-(H23*B23)) -> 0 | J23: =IF(G23=0,IF(F23=0,,H23*(1+F23)*C23-(H23*B23)),H23*(1+G23)*C23-(H23*B23)) -> 0
A24: RS | B24: =VLOOKUP(A24,[1]DIFAL!$C$13:$E$39,3,0) -> 0.12 | C24: 0.17 | H24: =PREÇOS!J25 -> 5.8425 | I24: =IF(F24=0,,H24*(1+F24)*C24-(H24*B24)) -> 0 | J24: =IF(G24=0,IF(F24=0,,H24*(1+F24)*C24-(H24*B24)),H24*(1+G24)*C24-(H24*B24)) -> 0
A25: SC | B25: =VLOOKUP(A25,[1]DIFAL!$C$13:$E$39,3,0) -> 0.12 | C25: 0.17 | H25: =PREÇOS!J26 -> 5.8425 | I25: =IF(F25=0,,H25*(1+F25)*C25-(H25*B25)) -> 0 | J25: =IF(G25=0,IF(F25=0,,H25*(1+F25)*C25-(H25*B25)),H25*(1+G25)*C25-(H25*B25)) -> 0
A26: SE | B26: =VLOOKUP(A26,[1]DIFAL!$C$13:$E$39,3,0) -> 0.07 | C26: 0.2 | H26: =PREÇOS!J27 -> 6.0325 | I26: =IF(F26=0,,H26*(1+F26)*C26-(H26*B26)) -> 0 | J26: =IF(G26=0,IF(F26=0,,H26*(1+F26)*C26-(H26*B26)),H26*(1+G26)*C26-(H26*B26)) -> 0
A27: SP | B27: =VLOOKUP(A27,[1]DIFAL!$C$13:$E$39,3,0) -> 0.12 | C27: 0.18 | F27: 0.463 | H27: =PREÇOS!J28 -> 5.8425 | I27: =IF(F27=0,,H27*(1+F27)*C27-(H27*B27)) -> 0.83746395 | J27: =IF(G27=0,IF(F27=0,,H27*(1+F27)*C27-(H27*B27)),H27*(1+G27)*C27-(H27*B27)) -> 0.83746395
A28: SP/Atacado | B28: =B27 -> 0.12 | C28: =C27 -> 0.18 | D28: =D27 -> 0 | E28: =E27 -> 0 | F28: =F27 -> 0.463 | G28: =G27 -> 0 | H28: =PREÇOS!J29 -> 5.8425 | I28: =IF(F28=0,,H28*(1+F28)*C28-(H28*B28)) -> 0.83746395 | J28: =IF(G28=0,IF(F28=0,,H28*(1+F28)*C28-(H28*B28)),H28*(1+G28)*C28-(H28*B28)) -> 0.83746395
A29: TO | B29: =VLOOKUP(A29,[1]DIFAL!$C$13:$E$39,3,0) -> 0.07 | C29: 0.2 | H29: =PREÇOS!J30 -> 6.0325 | I29: =IF(F29=0,,H29*(1+F29)*C29-(H29*B29)) -> 0 | J29: =IF(G29=0,IF(F29=0,,H29*(1+F29)*C29-(H29*B29)),H29*(1+G29)*C29-(H29*B29)) -> 0
A30: EX | H30: =PREÇOS!J31 -> 0 | I30: =IF(F30=0,,H30*(1+F30)*C30-(H30*B30)) -> 0 | J30: =IF(G30=0,IF(F30=0,,H30*(1+F30)*C30-(H30*B30)),H30*(1+G30)*C30-(H30*B30)) -> 0

Sheet ST MULTI 170 POUCH
A1: Estado | B1: Aliquota interestadual | C1: Aliquota interna | D1: MVA (normal) | E1: MVA (simples) | F1: Ajustada (normal) | G1: Ajustada (simples) | H1: Preço | I1: ST Normal | J1: ST Simples
A2: AC | B2: =VLOOKUP(A2,[1]DIFAL!$C$13:$E$39,3,0) -> 0.07 | C2: 0.17 | H2: =PREÇOS!K3 -> 4.9875 | I2: =IF(F2=0,,H2*(1+F2)*C2-(H2*B2)) -> 0 | J2: =IF(G2=0,IF(F2=0,,H2*(1+F2)*C2-(H2*B2)),H2*(1+G2)*C2-(H2*B2)) -> 0
A3: AL | B3: =VLOOKUP(A3,[1]DIFAL!$C$13:$E$39,3,0) -> 0.07 | C3: 0.2 | F3: 0.71 | H3: =PREÇOS!K4 -> 4.9875 | I3: =IF(F3=0,,H3*(1+F3)*C3-(H3*B3)) -> 1.3566 | J3: =IF(G3=0,IF(F3=0,,H3*(1+F3)*C3-(H3*B3)),H3*(1+G3)*C3-(H3*B3)) -> 1.3566
A4: AM | B4: =VLOOKUP(A4,[1]DIFAL!$C$13:$E$39,3,0) -> 0.07 | C4: 0.2 | F4: 0.5538 | H4: =PREÇOS!K5 -> 4.9875 | I4: =IF(F4=0,,H4*(1+F4)*C4-(H4*B4)) -> 1.2007905 | J4: =IF(G4=0,IF(F4=0,,H4*(1+F4)*C4-(H4*B4)),H4*(1+G4)*C4-(H4*B4)) -> 1.2007905
A5: AP | B5: =VLOOKUP(A5,[1]DIFAL!$C$13:$E$39,3,0) -> 0.07 | C5: 0.18 | H5: =PREÇOS!K6 -> 4.9875 | I5: =IF(F5=0,,H5*(1+F5)*C5-(H5*B5)) -> 0 | J5: =IF(G5=0,IF(F5=0,,H5*(1+F5)*C5-(H5*B5)),H5*(1+G5)*C5-(H5*B5)) -> 0
A6: BA | B6: =VLOOKUP(A6,[1]DIFAL!$C$13:$E$39,3,0) -> 0.07 | C6: 0.19 | H6: =PREÇOS!K7 -> 4.9875 | I6: =IF(F6=0,,H6*(1+F6)*C6-(H6*B6)) -> 0 | J6: =IF(G6=0,IF(F6=0,,H6*(1+F6)*C6-(H6*B6)),H6*(1+G6)*C6-(H6*B6)) -> 0
A7: CE | B7: =VLOOKUP(A7,[1]DIFAL!$C$13:$E$39,3,0) -> 0.07 | C7: 0.2 | H7: =PREÇOS!K8 -> 4.9875 | I7: =IF(F7=0,,H7*(1+F7)*C7-(H7*B7)) -> 0 | J7: =IF(G7=0,IF(F7=0,,H7*(1+F7)*C7-(H7*B7)),H7*(1+G7)*C7-(H7*B7)) -> 0
A8: DF | B8: =VLOOKUP(A8,[1]DIFAL!$C$13:$E$39,3,0) -> 0.07 | C8: 0.18 | H8: =PREÇOS!K9 -> 4.9875 | I8: =IF(F8=0,,H8*(1+F8)*C8-(H8*B8)) -> 0 | J8: =IF(G8=0,IF(F8=0,,H8*(1+F8)*C8-(H8*B8)),H8*(1+G8)*C8-(H8*B8)) -> 0
A9: ES | B9: =VLOOKUP(A9,[1]DIFAL!$C$13:$E$39,3,0) -> 0.07 | C9: 0.17 | H9: =PREÇOS!K10 -> 5.529 | I9: =IF(F9=0,,H9*(1+F9)*C9-(H9*B9)) -> 0 | J9: =IF(G9=0,IF(F9=0,,H9*(1+F9)*C9-(H9*B9)),H9*(1+G9)*C9-(H9*B9)) -> 0
A10: GO | B10: =VLOOKUP(A10,[1]DIFAL!$C$13:$E$39,3,0) -> 0.07 | C10: 0.17 | H10: =PREÇOS!K11 -> 4.9875 | I10: =IF(F10=0,,H10*(1+F10)*C10-(H10*B10)) -> 0 | J10: =IF(G10=0,IF(F10=0,,H10*(1+F10)*C10-(H10*B10)),H10*(1+G10)*C10-(H10*B10)) -> 0
A11: MA | B11: =VLOOKUP(A11,[1]DIFAL!$C$13:$E$39,3,0) -> 0.07 | C11: 0.2 | H11: =PREÇOS!K12 -> 4.9875 | I11: =IF(F11=0,,H11*(1+F11)*C11-(H11*B11)) -> 0 | J11: =IF(G11=0,IF(F11=0,,H11*(1+F11)*C11-(H11*B11)),H11*(1+G11)*C11-(H11*B11)) -> 0
A12: MG | B12: =VLOOKUP(A12,[1]DIFAL!$C$13:$E$39,3,0) -> 0.12 | C12: 0.18 | F12: 0.4488 | H12: =PREÇOS!K13 -> 5.8425 | I12: =IF(F12=0,,H12*(1+F12)*C12-(H12*B12)) -> 0.82253052 | J12: =IF(G12=0,IF(F12=0,,H12*(1+F12)*C12-(H12*B12)),H12*(1+G12)*C12-(H12*B12)) -> 0.82253052
A13: MS | B13: =VLOOKUP(A13,[1]DIFAL!$C$13:$E$39,3,0) -> 0.07 | C13: 0.17 | H13: =PREÇOS!K14 -> 4.9875 | I13: =IF(F13=0,,H13*(1+F13)*C13-(H13*B13)) -> 0 | J13: =IF(G13=0,IF(F13=0,,H13*(1+F13)*C13-(H13*B13)),H13*(1+G13)*C13-(H13*B13)) -> 0
A14: MT | B14: =VLOOKUP(A14,[1]DIFAL!$C$13:$E$39,3,0) -> 0.07 | C14: 0.17 | F14: 0.4552 | H14: =PREÇOS!K15 -> 4.9875 | I14: =IF(F14=0,,H14*(1+F14)*C14-(H14*B14)) -> 0.8847027 | J14: =IF(G14=0,IF(F14=0,,H14*(1+F14)*C14-(H14*B14)),H14*(1+G14)*C14-(H14*B14)) -> 0.8847027
A15: PA | B15: =VLOOKUP(A15,[1]DIFAL!$C$13:$E$39,3,0) -> 0.07 | C15: 0.19 | H15: =PREÇOS!K16 -> 4.9875 | I15: =IF(F15=0,,H15*(1+F15)*C15-(H15*B15)) -> 0 | J15: =IF(G15=0,IF(F15=0,,H15*(1+F15)*C15-(H15*B15)),H15*(1+G15)*C15-(H15*B15)) -> 0
A16: PB | B16: =VLOOKUP(A16,[1]DIFAL!$C$13:$E$39,3,0) -> 0.07 | C16: 0.18 | H16: =PREÇOS!K17 -> 4.9875 | I16: =IF(F16=0,,H16*(1+F16)*C16-(H16*B16)) -> 0 | J16: =IF(G16=0,IF(F16=0,,H16*(1+F16)*C16-(H16*B16)),H16*(1+G16)*C16-(H16*B16)) -> 0
A17: PE | B17: =VLOOKUP(A17,[1]DIFAL!$C$13:$E$39,3,0) -> 0.07 | C17: 0.18 | H17: =PREÇOS!K18 -> 4.9875 | I17: =IF(F17=0,,H17*(1+F17)*C17-(H17*B17)) -> 0 | J17: =IF(G17=0,IF(F17=0,,H17*(1+F17)*C17-(H17*B17)),H17*(1+G17)*C17-(H17*B17)) -> 0
A18: PI | B18: =VLOOKUP(A18,[1]DIFAL!$C$13:$E$39,3,0) -> 0.07 | C18: 0.21 | H18: =PREÇOS!K19 -> 4.9875 | I18: =IF(F18=0,,H18*(1+F18)*C18-(H18*B18)) -> 0 | J18: =IF(G18=0,IF(F18=0,,H18*(1+F18)*C18-(H18*B18)),H18*(1+G18)*C18-(H18*B18)) -> 0
A19: PR | B19: 0.12 | C19: 0.195 | F19: 0.608 | H19: =PREÇOS!K20 -> 5.8425 | I19: =IF(F19=0,,H19*(1+F19)*C19-(H19*B19)) -> 1.1308743 | J19: =IF(G19=0,IF(F19=0,,H19*(1+F19)*C19-(H19*B19)),H19*(1+G19)*C19-(H19*B19)) -> 1.1308743
A20: RJ | B20: =VLOOKUP(A20,[1]DIFAL!$C$13:$E$39,3,0) -> 0.12 | C20: 0.22 | F20: 0.5473 | H20: =PREÇOS!K21 -> 5.8425 | I20: =IF(F20=0,,H20*(1+F20)*C20-(H20*B20)) -> 1.2877221 | J20: =IF(G20=0,IF(F20=0,,H20*(1+F20)*C20-(H20*B20)),H20*(1+G20)*C20-(H20*B20)) -> 1.2877221
A21: RN | B21: =VLOOKUP(A21,[1]DIFAL!$C$13:$E$39,3,0) -> 0.07 | C21: 0.2 | H21: =PREÇOS!K22 -> 4.9875 | I21: =IF(F21=0,,H21*(1+F21)*C21-(H21*B21)) -> 0 | J21: =IF(G21=0,IF(F21=0,,H21*(1+F21)*C21-(H21*B21)),H21*(1+G21)*C21-(H21*B21)) -> 0
A22: RO | B22: =VLOOKUP(A22,[1]DIFAL!$C$13:$E$39,3,0) -> 0.07 | C22: 0.175 | H22: =PREÇOS!K23 -> 4.9875 | I22: =IF(F22=0,,H22*(1+F22)*C22-(H22*B22)) -> 0 | J22: =IF(G22=0,IF(F22=0,,H22*(1+F22)*C22-(H22*B22)),H22*(1+G22)*C22-(H22*B22)) -> 0
A23: RR | B23: =VLOOKUP(A23,[1]DIFAL!$C$13:$E$39,3,0) -> 0.07 | C23: 0.2 | H23: =PREÇOS!K24 -> 4.9875 | I23: =IF(F23=0,,H23*(1+F23)*C23-(H23*B23)) -> 0 | J23: =IF(G23=0,IF(F23=0,,H23*(1+F23)*C23-(H23*B23)),H23*(1+G23)*C23-(H23*B23)) -> 0
A24: RS | B24: =VLOOKUP(A24,[1]DIFAL!$C$13:$E$39,3,0) -> 0.12 | C24: 0.17 | H24: =PREÇOS!K25 -> 5.8425 | I24: =IF(F24=0,,H24*(1+F24)*C24-(H24*B24)) -> 0 | J24: =IF(G24=0,IF(F24=0,,H24*(1+F24)*C24-(H24*B24)),H24*(1+G24)*C24-(H24*B24)) -> 0
A25: SC | B25: =VLOOKUP(A25,[1]DIFAL!$C$13:$E$39,3,0) -> 0.12 | C25: 0.17 | H25: =PREÇOS!K26 -> 5.8425 | I25: =IF(F25=0,,H25*(1+F25)*C25-(H25*B25)) -> 0 | J25: =IF(G25=0,IF(F25=0,,H25*(1+F25)*C25-(H25*B25)),H25*(1+G25)*C25-(H25*B25)) -> 0
A26: SE | B26: =VLOOKUP(A26,[1]DIFAL!$C$13:$E$39,3,0) -> 0.07 | C26: 0.2 | H26: =PREÇOS!K27 -> 4.9875 | I26: =IF(F26=0,,H26*(1+F26)*C26-(H26*B26)) -> 0 | J26: =IF(G26=0,IF(F26=0,,H26*(1+F26)*C26-(H26*B26)),H26*(1+G26)*C26-(H26*B26)) -> 0
A27: SP | B27: =VLOOKUP(A27,[1]DIFAL!$C$13:$E$39,3,0) -> 0.12 | C27: 0.18 | F27: 0.463 | H27: =PREÇOS!K28 -> 5.8425 | I27: =IF(F27=0,,H27*(1+F27)*C27-(H27*B27)) -> 0.83746395 | J27: =IF(G27=0,IF(F27=0,,H27*(1+F27)*C27-(H27*B27)),H27*(1+G27)*C27-(H27*B27)) -> 0.83746395
A28: SP/Atacado | B28: =B27 -> 0.12 | C28: =C27 -> 0.18 | D28: =D27 -> 0 | E28: =E27 -> 0 | F28: =F27 -> 0.463 | G28: =G27 -> 0 | H28: =PREÇOS!K29 -> 5.8425 | I28: =IF(F28=0,,H28*(1+F28)*C28-(H28*B28)) -> 0.83746395 | J28: =IF(G28=0,IF(F28=0,,H28*(1+F28)*C28-(H28*B28)),H28*(1+G28)*C28-(H28*B28)) -> 0.83746395
A29: TO | B29: =VLOOKUP(A29,[1]DIFAL!$C$13:$E$39,3,0) -> 0.07 | C29: 0.2 | H29: =PREÇOS!K30 -> 4.9875 | I29: =IF(F29=0,,H29*(1+F29)*C29-(H29*B29)) -> 0 | J29: =IF(G29=0,IF(F29=0,,H29*(1+F29)*C29-(H29*B29)),H29*(1+G29)*C29-(H29*B29)) -> 0
A30: EX | H30: =PREÇOS!K31 -> 0 | I30: =IF(F30=0,,H30*(1+F30)*C30-(H30*B30)) -> 0 | J30: =IF(G30=0,IF(F30=0,,H30*(1+F30)*C30-(H30*B30)),H30*(1+G30)*C30-(H30*B30)) -> 0

Sheet ST MULTI 500 POUCH
A1: Estado | B1: Aliquota interestadual | C1: Aliquota interna | D1: MVA (normal) | E1: MVA (simples) | F1: Ajustada (normal) | G1: Ajustada (simples) | H1: Preço | I1: ST Normal | J1: ST Simples
A2: AC | B2: =VLOOKUP(A2,[1]DIFAL!$C$13:$E$39,3,0) -> 0.07 | C2: 0.17 | H2: =PREÇOS!L3 -> 12.73 | I2: =IF(F2=0,,H2*(1+F2)*C2-(H2*B2)) -> 0 | J2: =IF(G2=0,IF(F2=0,,H2*(1+F2)*C2-(H2*B2)),H2*(1+G2)*C2-(H2*B2)) -> 0
A3: AL | B3: =VLOOKUP(A3,[1]DIFAL!$C$13:$E$39,3,0) -> 0.07 | C3: 0.2 | F3: 0.71 | H3: =PREÇOS!L4 -> 12.73 | I3: =IF(F3=0,,H3*(1+F3)*C3-(H3*B3)) -> 3.46256 | J3: =IF(G3=0,IF(F3=0,,H3*(1+F3)*C3-(H3*B3)),H3*(1+G3)*C3-(H3*B3)) -> 3.46256
A4: AM | B4: =VLOOKUP(A4,[1]DIFAL!$C$13:$E$39,3,0) -> 0.07 | C4: 0.2 | F4: 0.5538 | H4: =PREÇOS!L5 -> 12.73 | I4: =IF(F4=0,,H4*(1+F4)*C4-(H4*B4)) -> 3.0648748 | J4: =IF(G4=0,IF(F4=0,,H4*(1+F4)*C4-(H4*B4)),H4*(1+G4)*C4-(H4*B4)) -> 3.0648748
A5: AP | B5: =VLOOKUP(A5,[1]DIFAL!$C$13:$E$39,3,0) -> 0.07 | C5: 0.18 | H5: =PREÇOS!L6 -> 12.73 | I5: =IF(F5=0,,H5*(1+F5)*C5-(H5*B5)) -> 0 | J5: =IF(G5=0,IF(F5=0,,H5*(1+F5)*C5-(H5*B5)),H5*(1+G5)*C5-(H5*B5)) -> 0
A6: BA | B6: =VLOOKUP(A6,[1]DIFAL!$C$13:$E$39,3,0) -> 0.07 | C6: 0.19 | H6: =PREÇOS!L7 -> 12.73 | I6: =IF(F6=0,,H6*(1+F6)*C6-(H6*B6)) -> 0 | J6: =IF(G6=0,IF(F6=0,,H6*(1+F6)*C6-(H6*B6)),H6*(1+G6)*C6-(H6*B6)) -> 0
A7: CE | B7: =VLOOKUP(A7,[1]DIFAL!$C$13:$E$39,3,0) -> 0.07 | C7: 0.2 | H7: =PREÇOS!L8 -> 12.73 | I7: =IF(F7=0,,H7*(1+F7)*C7-(H7*B7)) -> 0 | J7: =IF(G7=0,IF(F7=0,,H7*(1+F7)*C7-(H7*B7)),H7*(1+G7)*C7-(H7*B7)) -> 0
A8: DF | B8: =VLOOKUP(A8,[1]DIFAL!$C$13:$E$39,3,0) -> 0.07 | C8: 0.18 | H8: =PREÇOS!L9 -> 12.73 | I8: =IF(F8=0,,H8*(1+F8)*C8-(H8*B8)) -> 0 | J8: =IF(G8=0,IF(F8=0,,H8*(1+F8)*C8-(H8*B8)),H8*(1+G8)*C8-(H8*B8)) -> 0
A9: ES | B9: =VLOOKUP(A9,[1]DIFAL!$C$13:$E$39,3,0) -> 0.07 | C9: 0.17 | H9: =PREÇOS!L10 -> 13.471 | I9: =IF(F9=0,,H9*(1+F9)*C9-(H9*B9)) -> 0 | J9: =IF(G9=0,IF(F9=0,,H9*(1+F9)*C9-(H9*B9)),H9*(1+G9)*C9-(H9*B9)) -> 0
A10: GO | B10: =VLOOKUP(A10,[1]DIFAL!$C$13:$E$39,3,0) -> 0.07 | C10: 0.17 | H10: =PREÇOS!L11 -> 12.73 | I10: =IF(F10=0,,H10*(1+F10)*C10-(H10*B10)) -> 0 | J10: =IF(G10=0,IF(F10=0,,H10*(1+F10)*C10-(H10*B10)),H10*(1+G10)*C10-(H10*B10)) -> 0
A11: MA | B11: =VLOOKUP(A11,[1]DIFAL!$C$13:$E$39,3,0) -> 0.07 | C11: 0.2 | H11: =PREÇOS!L12 -> 12.73 | I11: =IF(F11=0,,H11*(1+F11)*C11-(H11*B11)) -> 0 | J11: =IF(G11=0,IF(F11=0,,H11*(1+F11)*C11-(H11*B11)),H11*(1+G11)*C11-(H11*B11)) -> 0
A12: MG | B12: =VLOOKUP(A12,[1]DIFAL!$C$13:$E$39,3,0) -> 0.12 | C12: 0.18 | F12: 0.4488 | H12: =PREÇOS!L13 -> 14.2405 | I12: =IF(F12=0,,H12*(1+F12)*C12-(H12*B12)) -> 2.0048346 | J12: =IF(G12=0,IF(F12=0,,H12*(1+F12)*C12-(H12*B12)),H12*(1+G12)*C12-(H12*B12)) -> 2.0048346
A13: MS | B13: =VLOOKUP(A13,[1]DIFAL!$C$13:$E$39,3,0) -> 0.07 | C13: 0.17 | H13: =PREÇOS!L14 -> 12.73 | I13: =IF(F13=0,,H13*(1+F13)*C13-(H13*B13)) -> 0 | J13: =IF(G13=0,IF(F13=0,,H13*(1+F13)*C13-(H13*B13)),H13*(1+G13)*C13-(H13*B13)) -> 0
A14: MT | B14: =VLOOKUP(A14,[1]DIFAL!$C$13:$E$39,3,0) -> 0.07 | C14: 0.17 | F14: 0.4552 | H14: =PREÇOS!L15 -> 12.73 | I14: =IF(F14=0,,H14*(1+F14)*C14-(H14*B14)) -> 2.2580983 | J14: =IF(G14=0,IF(F14=0,,H14*(1+F14)*C14-(H14*B14)),H14*(1+G14)*C14-(H14*B14)) -> 2.2580983
A15: PA | B15: =VLOOKUP(A15,[1]DIFAL!$C$13:$E$39,3,0) -> 0.07 | C15: 0.19 | H15: =PREÇOS!L16 -> 12.73 | I15: =IF(F15=0,,H15*(1+F15)*C15-(H15*B15)) -> 0 | J15: =IF(G15=0,IF(F15=0,,H15*(1+F15)*C15-(H15*B15)),H15*(1+G15)*C15-(H15*B15)) -> 0
A16: PB | B16: =VLOOKUP(A16,[1]DIFAL!$C$13:$E$39,3,0) -> 0.07 | C16: 0.18 | H16: =PREÇOS!L17 -> 12.73 | I16: =IF(F16=0,,H16*(1+F16)*C16-(H16*B16)) -> 0 | J16: =IF(G16=0,IF(F16=0,,H16*(1+F16)*C16-(H16*B16)),H16*(1+G16)*C16-(H16*B16)) -> 0
A17: PE | B17: =VLOOKUP(A17,[1]DIFAL!$C$13:$E$39,3,0) -> 0.07 | C17: 0.18 | H17: =PREÇOS!L18 -> 12.73 | I17: =IF(F17=0,,H17*(1+F17)*C17-(H17*B17)) -> 0 | J17: =IF(G17=0,IF(F17=0,,H17*(1+F17)*C17-(H17*B17)),H17*(1+G17)*C17-(H17*B17)) -> 0
A18: PI | B18: =VLOOKUP(A18,[1]DIFAL!$C$13:$E$39,3,0) -> 0.07 | C18: 0.21 | H18: =PREÇOS!L19 -> 12.73 | I18: =IF(F18=0,,H18*(1+F18)*C18-(H18*B18)) -> 0 | J18: =IF(G18=0,IF(F18=0,,H18*(1+F18)*C18-(H18*B18)),H18*(1+G18)*C18-(H18*B18)) -> 0
A19: PR | B19: 0.12 | C19: 0.195 | F19: 0.608 | H19: =PREÇOS!L20 -> 14.2405 | I19: =IF(F19=0,,H19*(1+F19)*C19-(H19*B19)) -> 2.7563912 | J19: =IF(G19=0,IF(F19=0,,H19*(1+F19)*C19-(H19*B19)),H19*(1+G19)*C19-(H19*B19)) -> 2.7563912
A20: RJ | B20: =VLOOKUP(A20,[1]DIFAL!$C$13:$E$39,3,0) -> 0.12 | C20: 0.22 | F20: 0.5473 | H20: =PREÇOS!L21 -> 14.2405 | I20: =IF(F20=0,,H20*(1+F20)*C20-(H20*B20)) -> 3.1386916 | J20: =IF(G20=0,IF(F20=0,,H20*(1+F20)*C20-(H20*B20)),H20*(1+G20)*C20-(H20*B20)) -> 3.1386916
A21: RN | B21: =VLOOKUP(A21,[1]DIFAL!$C$13:$E$39,3,0) -> 0.07 | C21: 0.2 | H21: =PREÇOS!L22 -> 12.73 | I21: =IF(F21=0,,H21*(1+F21)*C21-(H21*B21)) -> 0 | J21: =IF(G21=0,IF(F21=0,,H21*(1+F21)*C21-(H21*B21)),H21*(1+G21)*C21-(H21*B21)) -> 0
A22: RO | B22: =VLOOKUP(A22,[1]DIFAL!$C$13:$E$39,3,0) -> 0.07 | C22: 0.175 | H22: =PREÇOS!L23 -> 12.73 | I22: =IF(F22=0,,H22*(1+F22)*C22-(H22*B22)) -> 0 | J22: =IF(G22=0,IF(F22=0,,H22*(1+F22)*C22-(H22*B22)),H22*(1+G22)*C22-(H22*B22)) -> 0
A23: RR | B23: =VLOOKUP(A23,[1]DIFAL!$C$13:$E$39,3,0) -> 0.07 | C23: 0.2 | H23: =PREÇOS!L24 -> 12.73 | I23: =IF(F23=0,,H23*(1+F23)*C23-(H23*B23)) -> 0 | J23: =IF(G23=0,IF(F23=0,,H23*(1+F23)*C23-(H23*B23)),H23*(1+G23)*C23-(H23*B23)) -> 0
A24: RS | B24: =VLOOKUP(A24,[1]DIFAL!$C$13:$E$39,3,0) -> 0.12 | C24: 0.17 | H24: =PREÇOS!L25 -> 14.2405 | I24: =IF(F24=0,,H24*(1+F24)*C24-(H24*B24)) -> 0 | J24: =IF(G24=0,IF(F24=0,,H24*(1+F24)*C24-(H24*B24)),H24*(1+G24)*C24-(H24*B24)) -> 0
A25: SC | B25: =VLOOKUP(A25,[1]DIFAL!$C$13:$E$39,3,0) -> 0.12 | C25: 0.17 | H25: =PREÇOS!L26 -> 14.2405 | I25: =IF(F25=0,,H25*(1+F25)*C25-(H25*B25)) -> 0 | J25: =IF(G25=0,IF(F25=0,,H25*(1+F25)*C25-(H25*B25)),H25*(1+G25)*C25-(H25*B25)) -> 0
A26: SE | B26: =VLOOKUP(A26,[1]DIFAL!$C$13:$E$39,3,0) -> 0.07 | C26: 0.2 | H26: =PREÇOS!L27 -> 12.73 | I26: =IF(F26=0,,H26*(1+F26)*C26-(H26*B26)) -> 0 | J26: =IF(G26=0,IF(F26=0,,H26*(1+F26)*C26-(H26*B26)),H26*(1+G26)*C26-(H26*B26)) -> 0
A27: SP | B27: =VLOOKUP(A27,[1]DIFAL!$C$13:$E$39,3,0) -> 0.12 | C27: 0.18 | F27: 0.463 | H27: =PREÇOS!L28 -> 14.2405 | I27: =IF(F27=0,,H27*(1+F27)*C27-(H27*B27)) -> 2.0412333 | J27: =IF(G27=0,IF(F27=0,,H27*(1+F27)*C27-(H27*B27)),H27*(1+G27)*C27-(H27*B27)) -> 2.0412333
A28: SP/Atacado | B28: =B27 -> 0.12 | C28: =C27 -> 0.18 | D28: =D27 -> 0 | E28: =E27 -> 0 | F28: =F27 -> 0.463 | G28: =G27 -> 0 | H28: =PREÇOS!L29 -> 14.2405 | I28: =IF(F28=0,,H28*(1+F28)*C28-(H28*B28)) -> 2.0412333 | J28: =IF(G28=0,IF(F28=0,,H28*(1+F28)*C28-(H28*B28)),H28*(1+G28)*C28-(H28*B28)) -> 2.0412333
A29: TO | B29: =VLOOKUP(A29,[1]DIFAL!$C$13:$E$39,3,0) -> 0.07 | C29: 0.2 | H29: =PREÇOS!L30 -> 12.73 | I29: =IF(F29=0,,H29*(1+F29)*C29-(H29*B29)) -> 0 | J29: =IF(G29=0,IF(F29=0,,H29*(1+F29)*C29-(H29*B29)),H29*(1+G29)*C29-(H29*B29)) -> 0
A30: EX | H30: =PREÇOS!L31 -> 0 | I30: =IF(F30=0,,H30*(1+F30)*C30-(H30*B30)) -> 0 | J30: =IF(G30=0,IF(F30=0,,H30*(1+F30)*C30-(H30*B30)),H30*(1+G30)*C30-(H30*B30)) -> 0

Sheet PREÇOS
A1: 0325E | B1: ESPECIAL | D1: Preços atualizados 03 MAR 25
A2: Estado | B2: Papinhas | C2: Palitinhos | D2: Biscoitinhos | E2: Papapasta | F2: La Chef | G2: Linha Cerais | H2: Biscotti | I2: Pouch Carne | J2: P. Cereal 170g Sache sabores | K2: P. Cereal 170g Sache MULTI | L2: MULTI sache 500 g | M2: Yoguzinho | N2: Bowl | O2: Novos Biscotti | Q2: Estado | R2: Papinhas | S2: Palitinhos | T2: Biscoitinhos | U2: Papapasta | V2: La Chef | W2: Linha Cerais | X2: Biscotti | Y2: Pouch Carne | Z2: P. Cereal 170g Sache sabores | AA2: P. Cereal 170g Sache MULTI | AB2: MULTI sache 500 g | AC2: Yoguzinho | AD2: Bowl | AE2: Novos Biscotti
A3: AC | B3: =R3*0.95 -> 5.3865 | C3: =S3*0.95 -> 3.3915 | D3: =T3*0.95 -> 10.8965 | E3: =U3*0.95 -> 7.5335 | F3: =V3*0.95 -> 10.545 | G3: =W3*0.95 -> 7.4575 | H3: =X3*0.95 -> 7.5335 | I3: =Y3*0.95 -> 6.9825 | ... N3: =AD3*0.95 -> 10.773 | Q3: AC | R3: 5.67 | S3: 3.57 | T3: 11.47 | U3: 7.93 | V3: 11.1 | W3: 7.85 | X3: 7.93 | Y3: 7.35 | Z3: 6.35 | AA3: 5.25 | AB3: 13.4 | AC3: 5.67 | AD3: 11.34
A4: AL | B4: =R4*0.95 -> 5.3865 | C4: =S4*0.95 -> 3.3915 | D4: =T4*0.95 -> 10.8965 | E4: =U4*0.95 -> 7.5335 | F4: =V4*0.95 -> 10.545 | G4: =W4*0.95 -> 7.4575 | H4: =X4*0.95 -> 7.5335 | I4: =Y4*0.95 -> 6.9825 | ... N4: =AD4*0.95 -> 10.773 | Q4: AL | R4: 5.67 | S4: 3.57 | T4: 11.47 | U4: 7.93 | V4: 11.1 | W4: 7.85 | X4: 7.93 | Y4: 7.35 | Z4: 6.35 | AA4: 5.25 | AB4: 13.4 | AC4: 5.67 | AD4: 11.34
A5: AM | B5: =R5*0.95 -> 5.3865 | C5: =S5*0.95 -> 3.3915 | D5: =T5*0.95 -> 10.8965 | E5: =U5*0.95 -> 7.5335 | F5: =V5*0.95 -> 10.545 | G5: =W5*0.95 -> 7.4575 | H5: =X5*0.95 -> 7.5335 | I5: =Y5*0.95 -> 6.9825 | ... N5: =AD5*0.95 -> 10.773 | Q5: AM | R5: 5.67 | S5: 3.57 | T5: 11.47 | U5: 7.93 | V5: 11.1 | W5: 7.85 | X5: 7.93 | Y5: 7.35 | Z5: 6.35 | AA5: 5.25 | AB5: 13.4 | AC5: 5.67 | AD5: 11.34
A6: AP | B6: =R6*0.95 -> 5.3865 | C6: =S6*0.95 -> 3.3915 | D6: =T6*0.95 -> 10.8965 | E6: =U6*0.95 -> 7.5335 | F6: =V6*0.95 -> 10.545 | G6: =W6*0.95 -> 7.4575 | H6: =X6*0.95 -> 7.5335 | I6: =Y6*0.95 -> 6.9825 | ... N6: =AD6*0.95 -> 10.773 | Q6: AP | R6: 5.67 | S6: 3.57 | T6: 11.47 | U6: 7.93 | V6: 11.1 | W6: 7.85 | X6: 7.93 | Y6: 7.35 | Z6: 6.35 | AA6: 5.25 | AB6: 13.4 | AC6: 5.67 | AD6: 11.34
A7: BA | B7: =R7*0.95 -> 5.3865 | C7: =S7*0.95 -> 3.3915 | D7: =T7*0.95 -> 10.8965 | E7: =U7*0.95 -> 7.5335 | F7: =V7*0.95 -> 10.545 | G7: =W7*0.95 -> 7.4575 | H7: =X7*0.95 -> 7.5335 | I7: =Y7*0.95 -> 6.9825 | ... N7: =AD7*0.95 -> 10.773 | Q7: BA | R7: 5.67 | S7: 3.57 | T7: 11.47 | U7: 7.93 | V7: 11.1 | W7: 7.85 | X7: 7.93 | Y7: 7.35 | Z7: 6.35 | AA7: 5.25 | AB7: 13.4 | AC7: 5.67 | AD7: 11.34
A8: CE | B8: =R8*0.95 -> 5.3865 | C8: =S8*0.95 -> 3.3915 | D8: =T8*0.95 -> 10.8965 | E8: =U8*0.95 -> 7.5335 | F8: =V8*0.95 -> 10.545 | G8: =W8*0.95 -> 7.4575 | H8: =X8*0.95 -> 7.5335 | I8: =Y8*0.95 -> 6.9825 | ... N8: =AD8*0.95 -> 10.773 | Q8: CE | R8: 5.67 | S8: 3.57 | T8: 11.47 | U8: 7.93 | V8: 11.1 | W8: 7.85 | X8: 7.93 | Y8: 7.35 | Z8: 6.35 | AA8: 5.25 | AB8: 13.4 | AC8: 5.67 | AD8: 11.34
A9: DF | B9: =R9*0.95 -> 5.3865 | C9: =S9*0.95 -> 3.3915 | D9: =T9*0.95 -> 10.8965 | E9: =U9*0.95 -> 7.5335 | F9: =V9*0.95 -> 10.545 | G9: =W9*0.95 -> 7.4575 | H9: =X9*0.95 -> 7.5335 | I9: =Y9*0.95 -> 6.9825 | ... N9: =AD9*0.95 -> 10.773 | Q9: DF | R9: 5.67 | S9: 3.57 | T9: 11.47 | U9: 7.93 | V9: 11.1 | W9: 7.85 | X9: 7.93 | Y9: 7.35 | Z9: 6.35 | AA9: 5.25 | AB9: 13.4 | AC9: 5.67 | AD9: 11.34
A10: ES | B10: =R10*0.95 -> 5.3865 | C10: =S10*0.95 -> 3.3915 | D10: =T10*0.95 -> 10.8965 | E10: =U10*0.95 -> 7.5335 | F10: =V10*0.95 -> 10.545 | G10: =W10*0.95 -> 7.4575 | H10: =X10*0.95 -> 7.5335 | I10: =Y10*0.95 -> 6.9825 | ... N10: =AD10*0.95 -> 10.773 | Q10: ES | R10: 5.67 | S10: 3.57 | T10: 11.47 | U10: 7.93 | V10: 11.1 | W10: 7.85 | X10: 7.93 | Y10: 7.35 | Z10: 5.82 | AA10: 5.82 | AB10: 14.18 | AC10: 5.67 | AD10: 11.34
A11: GO | B11: =R11*0.95 -> 5.3865 | C11: =S11*0.95 -> 3.3915 | D11: =T11*0.95 -> 10.8965 | E11: =U11*0.95 -> 7.5335 | F11: =V11*0.95 -> 10.545 | G11: =W11*0.95 -> 7.4575 | H11: =X11*0.95 -> 7.5335 | I11: =Y11*0.95 -> 6.9825 | ... N11: =AD11*0.95 -> 10.773 | Q11: GO | R11: 5.67 | S11: 3.57 | T11: 11.47 | U11: 7.93 | V11: 11.1 | W11: 7.85 | X11: 7.93 | Y11: 7.35 | Z11: 6.35 | AA11: 5.25 | AB11: 13.4 | AC11: 5.67 | AD11: 11.34
A12: MA | B12: =R12*0.95 -> 5.3865 | C12: =S12*0.95 -> 3.3915 | D12: =T12*0.95 -> 10.8965 | E12: =U12*0.95 -> 7.5335 | F12: =V12*0.95 -> 10.545 | G12: =W12*0.95 -> 7.4575 | H12: =X12*0.95 -> 7.5335 | I12: =Y12*0.95 -> 6.9825 | ... N12: =AD12*0.95 -> 10.773 | Q12: MA | R12: 5.67 | S12: 3.57 | T12: 11.47 | U12: 7.93 | V12: 11.1 | W12: 7.85 | X12: 7.93 | Y12: 7.35 | Z12: 6.35 | AA12: 5.25 | AB12: 13.4 | AC12: 5.67 | AD12: 11.34
A13: MG | B13: =R13*0.95 -> 5.3865 | C13: =S13*0.95 -> 3.591 | D13: =T13*0.95 -> 10.8965 | E13: =U13*0.95 -> 8.0275 | F13: =V13*0.95 -> 11.21 | G13: =W13*0.95 -> 7.885 | H13: =X13*0.95 -> 7.98 | I13: =Y13*0.95 -> 6.9825 | ... N13: =AD13*0.95 -> 11.704 | Q13: MG | R13: 5.67 | S13: 3.78 | T13: 11.47 | U13: 8.45 | V13: 11.8 | W13: 8.3 | X13: 8.4 | Y13: 7.35 | Z13: 6.15 | AA13: 6.15 | AB13: 14.99 | AC13: 5.67 | AD13: 12.32
A14: MS | B14: =R14*0.95 -> 5.3865 | C14: =S14*0.95 -> 3.3915 | D14: =T14*0.95 -> 10.8965 | E14: =U14*0.95 -> 7.5335 | F14: =V14*0.95 -> 10.545 | G14: =W14*0.95 -> 7.4575 | H14: =X14*0.95 -> 7.5335 | I14: =Y14*0.95 -> 6.9825 | ... N14: =AD14*0.95 -> 10.773 | Q14: MS | R14: 5.67 | S14: 3.57 | T14: 11.47 | U14: 7.93 | V14: 11.1 | W14: 7.85 | X14: 7.93 | Y14: 7.35 | Z14: 6.35 | AA14: 5.25 | AB14: 13.4 | AC14: 5.67 | AD14: 11.34
... A30: TO | B30: =R30*0.95 -> 5.3865 | C30: =S30*0.95 -> 3.3915 | D30: =T30*0.95 -> 10.8965 | E30: =U30*0.95 -> 7.5335 | F30: =V30*0.95 -> 10.545 | G30: =W30*0.95 -> 7.4575 | H30: =X30*0.95 -> 7.5335 | I30: =Y30*0.95 -> 6.9825 | ... N30: =AD30*0.95 -> 10.773 | Q30: TO | R30: 5.67 | S30: 3.57 | T30: 11.47 | U30: 7.93 | V30: 11.1 | W30: 7.85 | X30: 7.93 | Y30: 7.35 | Z30: 6.35 | AA30: 5.25 | AB30: 13.4 | AC30: 5.67 | AD30: 11.34
A33: PSC | B33: 9.49 | C33: 5.99 | D33: 19.49 | E33: 12.99 | F33: 18.99 | G33: 14.39 | H33: 13.49 | I33: 12.49 | J33: 10.99 | K33: 10.99 | L33: 25.49 | M33: 9.49 | N33: 18.99 | Q33: PSC | R33: 9.49 | S33: 5.99 | T33: 19.49 | U33: 12.99 | V33: 18.99 | W33: 14.39 | X33: 13.49 | Y33: 12.49 | Z33: 10.99 | AA33: 10.99 | AB33: 25.49 | AC33: 9.49 | AD33: 18.99

Sheet PSC
A1: CONSUMIDOR | B1: CONSUMIDOR | C1: CONSUMIDOR | D1: CONSUMIDOR | E1: CONSUMIDOR | F1: CONSUMIDOR | G1: CONSUMIDOR | H1: CONSUMIDOR | I1: CONSUMIDOR | J1: CONSUMIDOR | K1: CONSUMIDOR | L1: CONSUMIDOR | M1: CONSUMIDOR | N1: CONSUMIDOR | O1: CONSUMIDOR
A2: Estado | B2: Papinhas | C2: Palitinhos | D2: Biscoitinhos | E2: Papapasta | F2: La Chef | G2: Linha Cerais | H2: Biscotti | I2: Pouch Carne | J2: P. Cereal 170g Sache sabores | K2: P. Cereal 170g Sache MULTI | L2: MULTI sache 500 g | M2: Yoguzinho | N2: Bowl | O2: Novos Biscotti
A3: AC | B3: 9.49 | C3: 5.79 | D3: 19.99 | E3: 13.69 | F3: 17.99 | G3: 13.89 | H3: 13.49 | I3: 12.49 | J3: 8.99 | K3: 7.99 | L3: 19.99 | M3: 9.49 | N3: 18.99
A4: AL | B4: 9.49 | C4: 5.79 | D4: 19.99 | E4: 13.69 | F4: 17.99 | G4: 13.89 | H4: 13.49 | I4: 12.49 | J4: 8.99 | K4: 7.99 | L4: 19.99 | M4: 9.49 | N4: 18.99
A5: AM | B5: 9.49 | C5: 5.79 | D5: 19.99 | E5: 13.69 | F5: 17.99 | G5: 13.89 | H5: 13.49 | I5: 12.49 | J5: 8.99 | K5: 7.99 | L5: 19.99 | M5: 9.49 | N5: 18.99
A6: AP | B6: 9.49 | C6: 5.79 | D6: 19.99 | E6: 13.69 | F6: 17.99 | G6: 13.89 | H6: 13.49 | I6: 12.49 | J6: 8.99 | K6: 7.99 | L6: 19.99 | M6: 9.49 | N6: 18.99
A7: BA | B7: 9.49 | C7: 5.79 | D7: 19.99 | E7: 13.69 | F7: 17.99 | G7: 13.89 | H7: 13.49 | I7: 12.49 | J7: 8.99 | K7: 7.99 | L7: 19.99 | M7: 9.49 | N7: 18.99
A8: CE | B8: 9.49 | C8: 5.79 | D8: 19.99 | E8: 13.69 | F8: 17.99 | G8: 13.89 | H8: 13.49 | I8: 12.49 | J8: 8.99 | K8: 7.99 | L8: 19.99 | M8: 9.49 | N8: 18.99
A9: DF | B9: 9.49 | C9: 5.79 | D9: 19.99 | E9: 13.69 | F9: 17.99 | G9: 13.89 | H9: 13.49 | I9: 12.49 | J9: 8.99 | K9: 7.99 | L9: 19.99 | M9: 9.49 | N9: 18.99
A10: ES | B10: 9.49 | C10: 5.79 | D10: 19.99 | E10: 13.69 | F10: 17.99 | G10: 13.89 | H10: 13.49 | I10: 12.49 | J10: 9.99 | K10: 9.99 | L10: 24.99 | M10: 9.49 | N10: 18.99
A11: GO | B11: 9.49 | C11: 5.79 | D11: 19.99 | E11: 13.69 | F11: 17.99 | G11: 13.89 | H11: 13.49 | I11: 12.49 | J11: 8.99 | K11: 7.99 | L11: 19.99 | M11: 9.49 | N11: 18.99
A12: MA | B12: 9.49 | C12: 5.79 | D12: 19.99 | E12: 13.69 | F12: 17.99 | G12: 13.89 | H12: 13.49 | I12: 12.49 | J12: 8.99 | K12: 7.99 | L12: 19.99 | M12: 9.49 | N12: 18.99
A13: MG | B13: 9.49 | C13: 5.79 | D13: 19.99 | E13: 13.69 | F13: 17.99 | G13: 13.89 | H13: 13.49 | I13: 12.49 | J13: 9.99 | K13: 9.99 | L13: 24.99 | M13: 9.49 | N13: 18.99
A14: MS | B14: 9.49 | C14: 5.79 | D14: 19.99 | E14: 13.69 | F14: 17.99 | G14: 13.89 | H14: 13.49 | I14: 12.49 | J14: 8.99 | K14: 7.99 | L14: 19.99 | M14: 9.49 | N14: 18.99
... A30: TO | B30: 9.49 | C30: 5.79 | D30: 19.99 | E30: 13.69 | F30: 17.99 | G30: 13.89 | H30: 13.49 | I30: 12.49 | J30: 8.99 | K30: 7.99 | L30: 19.99 | M30: 9.49 | N30: 18.99
A31: EX | N31: 18.99
A33: PSC | B33: 9.49 | C33: 5.79 | D33: 19.99 | E33: 13.69 | F33: 17.99 | G33: 13.89 | H33: 13.49 | I33: 12.49 | J33: 9.99 | K33: 9.99 | L33: 24.99 | M33: 9.49 | N33: 18.99 | O33: 0
I34: icms 7% | J34: 8.99 | K34: 7.99 | L34: 19.99
